{
  "method": {
    "dense_q_matrix_stored": false,
    "principal_path": "exterior finite-Laurent kernel split with circle Q Fourier primitive",
    "bgk_repay": "sum_j (-beta sqrt(h))^j / j! * d_rho^j I(rho+beta sqrt(h))",
    "correction_orders": [
      1,
      2,
      4,
      8,
      16
    ],
    "zeta_half": -1.4603545088095868,
    "bgk_beta": 0.5825971579390108
  },
  "rows": [
    {
      "shape": "circle",
      "family": "identity exterior map",
      "n": 2048,
      "reference_n": 32768,
      "true_conformal_offset": 0.001,
      "monitor_h": 1.52587890625e-05,
      "bgk_beta": 0.5825971579390108,
      "bgk_shift": 0.002275770148199261,
      "correction_order": 0,
      "reference_value": -0.28881438523727193,
      "raw_discrete_value": -0.27311446379721227,
      "corrected_value": -0.27311446379721227,
      "rel_error": 0.054359901177226964
    },
    {
      "shape": "circle",
      "family": "identity exterior map",
      "n": 2048,
      "reference_n": 32768,
      "true_conformal_offset": 0.001,
      "monitor_h": 1.52587890625e-05,
      "bgk_beta": 0.5825971579390108,
      "bgk_shift": 0.002275770148199261,
      "correction_order": 1,
      "reference_value": -0.28881438523727193,
      "raw_discrete_value": -0.27311446379721227,
      "corrected_value": -0.28879648166272215,
      "rel_error": 6.198989892790124e-05
    },
    {
      "shape": "circle",
      "family": "identity exterior map",
      "n": 2048,
      "reference_n": 32768,
      "true_conformal_offset": 0.001,
      "monitor_h": 1.52587890625e-05,
      "bgk_beta": 0.5825971579390108,
      "bgk_shift": 0.002275770148199261,
      "correction_order": 2,
      "reference_value": -0.28881438523727193,
      "raw_discrete_value": -0.27311446379721227,
      "corrected_value": -0.28881436542838834,
      "rel_error": 6.858690079691168e-08
    },
    {
      "shape": "circle",
      "family": "identity exterior map",
      "n": 2048,
      "reference_n": 32768,
      "true_conformal_offset": 0.001,
      "monitor_h": 1.52587890625e-05,
      "bgk_beta": 0.5825971579390108,
      "bgk_shift": 0.002275770148199261,
      "correction_order": 4,
      "reference_value": -0.28881438523727193,
      "raw_discrete_value": -0.27311446379721227,
      "corrected_value": -0.2888143852374572,
      "rel_error": 6.415754625854622e-13
    },
    {
      "shape": "circle",
      "family": "identity exterior map",
      "n": 2048,
      "reference_n": 32768,
      "true_conformal_offset": 0.001,
      "monitor_h": 1.52587890625e-05,
      "bgk_beta": 0.5825971579390108,
      "bgk_shift": 0.002275770148199261,
      "correction_order": 8,
      "reference_value": -0.28881438523727193,
      "raw_discrete_value": -0.27311446379721227,
      "corrected_value": -0.2888143852372721,
      "rel_error": 5.766106614009546e-16
    },
    {
      "shape": "circle",
      "family": "identity exterior map",
      "n": 2048,
      "reference_n": 32768,
      "true_conformal_offset": 0.001,
      "monitor_h": 1.52587890625e-05,
      "bgk_beta": 0.5825971579390108,
      "bgk_shift": 0.002275770148199261,
      "correction_order": 16,
      "reference_value": -0.28881438523727193,
      "raw_discrete_value": -0.27311446379721227,
      "corrected_value": -0.2888143852372721,
      "rel_error": 5.766106614009546e-16
    },
    {
      "shape": "circle",
      "family": "identity exterior map",
      "n": 2048,
      "reference_n": 32768,
      "true_conformal_offset": 0.001,
      "monitor_h": 3.814697265625e-06,
      "bgk_beta": 0.5825971579390108,
      "bgk_shift": 0.0011378850740996304,
      "correction_order": 0,
      "reference_value": -0.28881438523727193,
      "raw_discrete_value": -0.280959946148006,
      "corrected_value": -0.280959946148006,
      "rel_error": 0.027195456634935965
    },
    {
      "shape": "circle",
      "family": "identity exterior map",
      "n": 2048,
      "reference_n": 32768,
      "true_conformal_offset": 0.001,
      "monitor_h": 3.814697265625e-06,
      "bgk_beta": 0.5825971579390108,
      "bgk_shift": 0.0011378850740996304,
      "correction_order": 1,
      "reference_value": -0.28881438523727193,
      "raw_discrete_value": -0.280959946148006,
      "corrected_value": -0.2888099043929565,
      "rel_error": 1.5514616114924813e-05
    },
    {
      "shape": "circle",
      "family": "identity exterior map",
      "n": 2048,
      "reference_n": 32768,
      "true_conformal_offset": 0.001,
      "monitor_h": 3.814697265625e-06,
      "bgk_beta": 0.5825971579390108,
      "bgk_shift": 0.0011378850740996304,
      "correction_order": 2,
      "reference_value": -0.28881438523727193,
      "raw_discrete_value": -0.280959946148006,
      "corrected_value": -0.28881438276271615,
      "rel_error": 8.567979674809895e-09
    },
    {
      "shape": "circle",
      "family": "identity exterior map",
      "n": 2048,
      "reference_n": 32768,
      "true_conformal_offset": 0.001,
      "monitor_h": 3.814697265625e-06,
      "bgk_beta": 0.5825971579390108,
      "bgk_shift": 0.0011378850740996304,
      "correction_order": 4,
      "reference_value": -0.28881438523727193,
      "raw_discrete_value": -0.280959946148006,
      "corrected_value": -0.28881438523727715,
      "rel_error": 1.8067134057229912e-14
    },
    {
      "shape": "circle",
      "family": "identity exterior map",
      "n": 2048,
      "reference_n": 32768,
      "true_conformal_offset": 0.001,
      "monitor_h": 3.814697265625e-06,
      "bgk_beta": 0.5825971579390108,
      "bgk_shift": 0.0011378850740996304,
      "correction_order": 8,
      "reference_value": -0.28881438523727193,
      "raw_discrete_value": -0.280959946148006,
      "corrected_value": -0.28881438523727126,
      "rel_error": 2.3064426456038186e-15
    },
    {
      "shape": "circle",
      "family": "identity exterior map",
      "n": 2048,
      "reference_n": 32768,
      "true_conformal_offset": 0.001,
      "monitor_h": 3.814697265625e-06,
      "bgk_beta": 0.5825971579390108,
      "bgk_shift": 0.0011378850740996304,
      "correction_order": 16,
      "reference_value": -0.28881438523727193,
      "raw_discrete_value": -0.280959946148006,
      "corrected_value": -0.28881438523727126,
      "rel_error": 2.3064426456038186e-15
    },
    {
      "shape": "circle",
      "family": "identity exterior map",
      "n": 2048,
      "reference_n": 32768,
      "true_conformal_offset": 0.001,
      "monitor_h": 9.5367431640625e-07,
      "bgk_beta": 0.5825971579390108,
      "bgk_shift": 0.0005689425370498152,
      "correction_order": 0,
      "reference_value": -0.28881438523727193,
      "raw_discrete_value": -0.28488604517227434,
      "corrected_value": -0.28488604517227434,
      "rel_error": 0.013601608042377505
    },
    {
      "shape": "circle",
      "family": "identity exterior map",
      "n": 2048,
      "reference_n": 32768,
      "true_conformal_offset": 0.001,
      "monitor_h": 9.5367431640625e-07,
      "bgk_beta": 0.5825971579390108,
      "bgk_shift": 0.0005689425370498152,
      "correction_order": 1,
      "reference_value": -0.28881438523727193,
      "raw_discrete_value": -0.28488604517227434,
      "corrected_value": -0.28881326440765437,
      "rel_error": 3.880795676578338e-06
    },
    {
      "shape": "circle",
      "family": "identity exterior map",
      "n": 2048,
      "reference_n": 32768,
      "true_conformal_offset": 0.001,
      "monitor_h": 9.5367431640625e-07,
      "bgk_beta": 0.5825971579390108,
      "bgk_shift": 0.0005689425370498152,
      "correction_order": 2,
      "reference_value": -0.28881438523727193,
      "raw_discrete_value": -0.28488604517227434,
      "corrected_value": -0.28881438492805284,
      "rel_error": 1.0706499072750775e-09
    },
    {
      "shape": "circle",
      "family": "identity exterior map",
      "n": 2048,
      "reference_n": 32768,
      "true_conformal_offset": 0.001,
      "monitor_h": 9.5367431640625e-07,
      "bgk_beta": 0.5825971579390108,
      "bgk_shift": 0.0005689425370498152,
      "correction_order": 4,
      "reference_value": -0.28881438523727193,
      "raw_discrete_value": -0.28488604517227434,
      "corrected_value": -0.28881438523727193,
      "rel_error": 0.0
    },
    {
      "shape": "circle",
      "family": "identity exterior map",
      "n": 2048,
      "reference_n": 32768,
      "true_conformal_offset": 0.001,
      "monitor_h": 9.5367431640625e-07,
      "bgk_beta": 0.5825971579390108,
      "bgk_shift": 0.0005689425370498152,
      "correction_order": 8,
      "reference_value": -0.28881438523727193,
      "raw_discrete_value": -0.28488604517227434,
      "corrected_value": -0.28881438523727176,
      "rel_error": 5.766106614009546e-16
    },
    {
      "shape": "circle",
      "family": "identity exterior map",
      "n": 2048,
      "reference_n": 32768,
      "true_conformal_offset": 0.001,
      "monitor_h": 9.5367431640625e-07,
      "bgk_beta": 0.5825971579390108,
      "bgk_shift": 0.0005689425370498152,
      "correction_order": 16,
      "reference_value": -0.28881438523727193,
      "raw_discrete_value": -0.28488604517227434,
      "corrected_value": -0.28881438523727176,
      "rel_error": 5.766106614009546e-16
    },
    {
      "shape": "circle",
      "family": "identity exterior map",
      "n": 2048,
      "reference_n": 32768,
      "true_conformal_offset": 0.001,
      "monitor_h": 2.384185791015625e-07,
      "bgk_beta": 0.5825971579390108,
      "bgk_shift": 0.0002844712685249076,
      "correction_order": 0,
      "reference_value": -0.28881438523727193,
      "raw_discrete_value": -0.28684993495871935,
      "corrected_value": -0.28684993495871935,
      "rel_error": 0.006801774353928757
    },
    {
      "shape": "circle",
      "family": "identity exterior map",
      "n": 2048,
      "reference_n": 32768,
      "true_conformal_offset": 0.001,
      "monitor_h": 2.384185791015625e-07,
      "bgk_beta": 0.5825971579390108,
      "bgk_shift": 0.0002844712685249076,
      "correction_order": 1,
      "reference_value": -0.28881438523727193,
      "raw_discrete_value": -0.28684993495871935,
      "corrected_value": -0.28881410495256993,
      "rel_error": 9.70466556827145e-07
    },
    {
      "shape": "circle",
      "family": "identity exterior map",
      "n": 2048,
      "reference_n": 32768,
      "true_conformal_offset": 0.001,
      "monitor_h": 2.384185791015625e-07,
      "bgk_beta": 0.5825971579390108,
      "bgk_shift": 0.0002844712685249076,
      "correction_order": 2,
      "reference_value": -0.28881438523727193,
      "raw_discrete_value": -0.28684993495871935,
      "corrected_value": -0.2888143851986267,
      "rel_error": 1.3380654025272133e-10
    },
    {
      "shape": "circle",
      "family": "identity exterior map",
      "n": 2048,
      "reference_n": 32768,
      "true_conformal_offset": 0.001,
      "monitor_h": 2.384185791015625e-07,
      "bgk_beta": 0.5825971579390108,
      "bgk_shift": 0.0002844712685249076,
      "correction_order": 4,
      "reference_value": -0.28881438523727193,
      "raw_discrete_value": -0.28684993495871935,
      "corrected_value": -0.28881438523727265,
      "rel_error": 2.4986461994041367e-15
    },
    {
      "shape": "circle",
      "family": "identity exterior map",
      "n": 2048,
      "reference_n": 32768,
      "true_conformal_offset": 0.001,
      "monitor_h": 2.384185791015625e-07,
      "bgk_beta": 0.5825971579390108,
      "bgk_shift": 0.0002844712685249076,
      "correction_order": 8,
      "reference_value": -0.28881438523727193,
      "raw_discrete_value": -0.28684993495871935,
      "corrected_value": -0.28881438523727265,
      "rel_error": 2.4986461994041367e-15
    },
    {
      "shape": "circle",
      "family": "identity exterior map",
      "n": 2048,
      "reference_n": 32768,
      "true_conformal_offset": 0.001,
      "monitor_h": 2.384185791015625e-07,
      "bgk_beta": 0.5825971579390108,
      "bgk_shift": 0.0002844712685249076,
      "correction_order": 16,
      "reference_value": -0.28881438523727193,
      "raw_discrete_value": -0.28684993495871935,
      "corrected_value": -0.28881438523727265,
      "rel_error": 2.4986461994041367e-15
    },
    {
      "shape": "circle",
      "family": "identity exterior map",
      "n": 2048,
      "reference_n": 32768,
      "true_conformal_offset": 0.001,
      "monitor_h": 5.960464477539063e-08,
      "bgk_beta": 0.5825971579390108,
      "bgk_shift": 0.0001422356342624538,
      "correction_order": 0,
      "reference_value": -0.28881438523727193,
      "raw_discrete_value": -0.2878320900219895,
      "corrected_value": -0.2878320900219895,
      "rel_error": 0.0034011298103293307
    },
    {
      "shape": "circle",
      "family": "identity exterior map",
      "n": 2048,
      "reference_n": 32768,
      "true_conformal_offset": 0.001,
      "monitor_h": 5.960464477539063e-08,
      "bgk_beta": 0.5825971579390108,
      "bgk_shift": 0.0001422356342624538,
      "correction_order": 1,
      "reference_value": -0.28881438523727193,
      "raw_discrete_value": -0.2878320900219895,
      "corrected_value": -0.2888143151564357,
      "rel_error": 2.4265008887176294e-07
    },
    {
      "shape": "circle",
      "family": "identity exterior map",
      "n": 2048,
      "reference_n": 32768,
      "true_conformal_offset": 0.001,
      "monitor_h": 5.960464477539063e-08,
      "bgk_beta": 0.5825971579390108,
      "bgk_shift": 0.0001422356342624538,
      "correction_order": 2,
      "reference_value": -0.28881438523727193,
      "raw_discrete_value": -0.2878320900219895,
      "corrected_value": -0.2888143852324421,
      "rel_error": 1.6723054605504287e-11
    },
    {
      "shape": "circle",
      "family": "identity exterior map",
      "n": 2048,
      "reference_n": 32768,
      "true_conformal_offset": 0.001,
      "monitor_h": 5.960464477539063e-08,
      "bgk_beta": 0.5825971579390108,
      "bgk_shift": 0.0001422356342624538,
      "correction_order": 4,
      "reference_value": -0.28881438523727193,
      "raw_discrete_value": -0.2878320900219895,
      "corrected_value": -0.28881438523727243,
      "rel_error": 1.729831984202864e-15
    },
    {
      "shape": "circle",
      "family": "identity exterior map",
      "n": 2048,
      "reference_n": 32768,
      "true_conformal_offset": 0.001,
      "monitor_h": 5.960464477539063e-08,
      "bgk_beta": 0.5825971579390108,
      "bgk_shift": 0.0001422356342624538,
      "correction_order": 8,
      "reference_value": -0.28881438523727193,
      "raw_discrete_value": -0.2878320900219895,
      "corrected_value": -0.28881438523727243,
      "rel_error": 1.729831984202864e-15
    },
    {
      "shape": "circle",
      "family": "identity exterior map",
      "n": 2048,
      "reference_n": 32768,
      "true_conformal_offset": 0.001,
      "monitor_h": 5.960464477539063e-08,
      "bgk_beta": 0.5825971579390108,
      "bgk_shift": 0.0001422356342624538,
      "correction_order": 16,
      "reference_value": -0.28881438523727193,
      "raw_discrete_value": -0.2878320900219895,
      "corrected_value": -0.28881438523727243,
      "rel_error": 1.729831984202864e-15
    },
    {
      "shape": "circle",
      "family": "identity exterior map",
      "n": 2048,
      "reference_n": 32768,
      "true_conformal_offset": 0.001,
      "monitor_h": 1.4901161193847656e-08,
      "bgk_beta": 0.5825971579390108,
      "bgk_shift": 7.11178171312269e-05,
      "correction_order": 0,
      "reference_value": -0.28881438523727193,
      "raw_discrete_value": -0.2883232201088171,
      "corrected_value": -0.2883232201088171,
      "rel_error": 0.001700625569780076
    },
    {
      "shape": "circle",
      "family": "identity exterior map",
      "n": 2048,
      "reference_n": 32768,
      "true_conformal_offset": 0.001,
      "monitor_h": 1.4901161193847656e-08,
      "bgk_beta": 0.5825971579390108,
      "bgk_shift": 7.11178171312269e-05,
      "correction_order": 1,
      "reference_value": -0.28881438523727193,
      "raw_discrete_value": -0.2883232201088171,
      "corrected_value": -0.2888143677158548,
      "rel_error": 6.06667051438821e-08
    },
    {
      "shape": "circle",
      "family": "identity exterior map",
      "n": 2048,
      "reference_n": 32768,
      "true_conformal_offset": 0.001,
      "monitor_h": 1.4901161193847656e-08,
      "bgk_beta": 0.5825971579390108,
      "bgk_shift": 7.11178171312269e-05,
      "correction_order": 2,
      "reference_value": -0.28881438523727193,
      "raw_discrete_value": -0.2883232201088171,
      "corrected_value": -0.2888143852366678,
      "rel_error": 2.0917512760088633e-12
    },
    {
      "shape": "circle",
      "family": "identity exterior map",
      "n": 2048,
      "reference_n": 32768,
      "true_conformal_offset": 0.001,
      "monitor_h": 1.4901161193847656e-08,
      "bgk_beta": 0.5825971579390108,
      "bgk_shift": 7.11178171312269e-05,
      "correction_order": 4,
      "reference_value": -0.28881438523727193,
      "raw_discrete_value": -0.2883232201088171,
      "corrected_value": -0.28881438523727154,
      "rel_error": 1.3454248766022276e-15
    },
    {
      "shape": "circle",
      "family": "identity exterior map",
      "n": 2048,
      "reference_n": 32768,
      "true_conformal_offset": 0.001,
      "monitor_h": 1.4901161193847656e-08,
      "bgk_beta": 0.5825971579390108,
      "bgk_shift": 7.11178171312269e-05,
      "correction_order": 8,
      "reference_value": -0.28881438523727193,
      "raw_discrete_value": -0.2883232201088171,
      "corrected_value": -0.28881438523727154,
      "rel_error": 1.3454248766022276e-15
    },
    {
      "shape": "circle",
      "family": "identity exterior map",
      "n": 2048,
      "reference_n": 32768,
      "true_conformal_offset": 0.001,
      "monitor_h": 1.4901161193847656e-08,
      "bgk_beta": 0.5825971579390108,
      "bgk_shift": 7.11178171312269e-05,
      "correction_order": 16,
      "reference_value": -0.28881438523727193,
      "raw_discrete_value": -0.2883232201088171,
      "corrected_value": -0.28881438523727154,
      "rel_error": 1.3454248766022276e-15
    },
    {
      "shape": "golden_ellipse",
      "family": "closed-form Joukowski ellipse",
      "n": 2048,
      "reference_n": 32768,
      "true_conformal_offset": 0.001,
      "monitor_h": 1.52587890625e-05,
      "bgk_beta": 0.5825971579390108,
      "bgk_shift": 0.002275770148199261,
      "correction_order": 0,
      "reference_value": 15.456635336324847,
      "raw_discrete_value": 15.497028428709369,
      "corrected_value": 15.497028428709369,
      "rel_error": 0.0026133172909626012
    },
    {
      "shape": "golden_ellipse",
      "family": "closed-form Joukowski ellipse",
      "n": 2048,
      "reference_n": 32768,
      "true_conformal_offset": 0.001,
      "monitor_h": 1.52587890625e-05,
      "bgk_beta": 0.5825971579390108,
      "bgk_shift": 0.002275770148199261,
      "correction_order": 1,
      "reference_value": 15.456635336324847,
      "raw_discrete_value": 15.497028428709369,
      "corrected_value": 15.45668356318123,
      "rel_error": 3.12013936621985e-06
    },
    {
      "shape": "golden_ellipse",
      "family": "closed-form Joukowski ellipse",
      "n": 2048,
      "reference_n": 32768,
      "true_conformal_offset": 0.001,
      "monitor_h": 1.52587890625e-05,
      "bgk_beta": 0.5825971579390108,
      "bgk_shift": 0.002275770148199261,
      "correction_order": 2,
      "reference_value": 15.456635336324847,
      "raw_discrete_value": 15.497028428709369,
      "corrected_value": 15.456635400889523,
      "rel_error": 4.177149423465715e-09
    },
    {
      "shape": "golden_ellipse",
      "family": "closed-form Joukowski ellipse",
      "n": 2048,
      "reference_n": 32768,
      "true_conformal_offset": 0.001,
      "monitor_h": 1.52587890625e-05,
      "bgk_beta": 0.5825971579390108,
      "bgk_shift": 0.002275770148199261,
      "correction_order": 4,
      "reference_value": 15.456635336324847,
      "raw_discrete_value": 15.497028428709369,
      "corrected_value": 15.456635336324497,
      "rel_error": 2.2640263533904123e-14
    },
    {
      "shape": "golden_ellipse",
      "family": "closed-form Joukowski ellipse",
      "n": 2048,
      "reference_n": 32768,
      "true_conformal_offset": 0.001,
      "monitor_h": 1.52587890625e-05,
      "bgk_beta": 0.5825971579390108,
      "bgk_shift": 0.002275770148199261,
      "correction_order": 8,
      "reference_value": 15.456635336324847,
      "raw_discrete_value": 15.497028428709369,
      "corrected_value": 15.456635336324766,
      "rel_error": 5.2865589977644146e-15
    },
    {
      "shape": "golden_ellipse",
      "family": "closed-form Joukowski ellipse",
      "n": 2048,
      "reference_n": 32768,
      "true_conformal_offset": 0.001,
      "monitor_h": 1.52587890625e-05,
      "bgk_beta": 0.5825971579390108,
      "bgk_shift": 0.002275770148199261,
      "correction_order": 16,
      "reference_value": 15.456635336324847,
      "raw_discrete_value": 15.497028428709369,
      "corrected_value": 15.456635336324766,
      "rel_error": 5.2865589977644146e-15
    },
    {
      "shape": "golden_ellipse",
      "family": "closed-form Joukowski ellipse",
      "n": 2048,
      "reference_n": 32768,
      "true_conformal_offset": 0.001,
      "monitor_h": 3.814697265625e-06,
      "bgk_beta": 0.5825971579390108,
      "bgk_shift": 0.0011378850740996304,
      "correction_order": 0,
      "reference_value": 15.456635336324847,
      "raw_discrete_value": 15.476843947304168,
      "corrected_value": 15.476843947304168,
      "rel_error": 0.001307439202620519
    },
    {
      "shape": "golden_ellipse",
      "family": "closed-form Joukowski ellipse",
      "n": 2048,
      "reference_n": 32768,
      "true_conformal_offset": 0.001,
      "monitor_h": 3.814697265625e-06,
      "bgk_beta": 0.5825971579390108,
      "bgk_shift": 0.0011378850740996304,
      "correction_order": 1,
      "reference_value": 15.456635336324847,
      "raw_discrete_value": 15.476843947304168,
      "corrected_value": 15.456647409187259,
      "rel_error": 7.810795912836221e-07
    },
    {
      "shape": "golden_ellipse",
      "family": "closed-form Joukowski ellipse",
      "n": 2048,
      "reference_n": 32768,
      "true_conformal_offset": 0.001,
      "monitor_h": 3.814697265625e-06,
      "bgk_beta": 0.5825971579390108,
      "bgk_shift": 0.0011378850740996304,
      "correction_order": 2,
      "reference_value": 15.456635336324847,
      "raw_discrete_value": 15.476843947304168,
      "corrected_value": 15.45663534440253,
      "rel_error": 5.226029046491968e-10
    },
    {
      "shape": "golden_ellipse",
      "family": "closed-form Joukowski ellipse",
      "n": 2048,
      "reference_n": 32768,
      "true_conformal_offset": 0.001,
      "monitor_h": 3.814697265625e-06,
      "bgk_beta": 0.5825971579390108,
      "bgk_shift": 0.0011378850740996304,
      "correction_order": 4,
      "reference_value": 15.456635336324847,
      "raw_discrete_value": 15.476843947304168,
      "corrected_value": 15.456635336324744,
      "rel_error": 6.665661345007306e-15
    },
    {
      "shape": "golden_ellipse",
      "family": "closed-form Joukowski ellipse",
      "n": 2048,
      "reference_n": 32768,
      "true_conformal_offset": 0.001,
      "monitor_h": 3.814697265625e-06,
      "bgk_beta": 0.5825971579390108,
      "bgk_shift": 0.0011378850740996304,
      "correction_order": 8,
      "reference_value": 15.456635336324847,
      "raw_discrete_value": 15.476843947304168,
      "corrected_value": 15.456635336324753,
      "rel_error": 6.091035366989434e-15
    },
    {
      "shape": "golden_ellipse",
      "family": "closed-form Joukowski ellipse",
      "n": 2048,
      "reference_n": 32768,
      "true_conformal_offset": 0.001,
      "monitor_h": 3.814697265625e-06,
      "bgk_beta": 0.5825971579390108,
      "bgk_shift": 0.0011378850740996304,
      "correction_order": 16,
      "reference_value": 15.456635336324847,
      "raw_discrete_value": 15.476843947304168,
      "corrected_value": 15.456635336324753,
      "rel_error": 6.091035366989434e-15
    },
    {
      "shape": "golden_ellipse",
      "family": "closed-form Joukowski ellipse",
      "n": 2048,
      "reference_n": 32768,
      "true_conformal_offset": 0.001,
      "monitor_h": 9.5367431640625e-07,
      "bgk_beta": 0.5825971579390108,
      "bgk_shift": 0.0005689425370498152,
      "correction_order": 0,
      "reference_value": 15.456635336324847,
      "raw_discrete_value": 15.466742661039932,
      "corrected_value": 15.466742661039932,
      "rel_error": 0.0006539149365406406
    },
    {
      "shape": "golden_ellipse",
      "family": "closed-form Joukowski ellipse",
      "n": 2048,
      "reference_n": 32768,
      "true_conformal_offset": 0.001,
      "monitor_h": 9.5367431640625e-07,
      "bgk_beta": 0.5825971579390108,
      "bgk_shift": 0.0005689425370498152,
      "correction_order": 1,
      "reference_value": 15.456635336324847,
      "raw_discrete_value": 15.466742661039932,
      "corrected_value": 15.456638356560243,
      "rel_error": 1.95400572595165e-07
    },
    {
      "shape": "golden_ellipse",
      "family": "closed-form Joukowski ellipse",
      "n": 2048,
      "reference_n": 32768,
      "true_conformal_offset": 0.001,
      "monitor_h": 9.5367431640625e-07,
      "bgk_beta": 0.5825971579390108,
      "bgk_shift": 0.0005689425370498152,
      "correction_order": 2,
      "reference_value": 15.456635336324847,
      "raw_discrete_value": 15.466742661039932,
      "corrected_value": 15.456635337334895,
      "rel_error": 6.534715577136593e-11
    },
    {
      "shape": "golden_ellipse",
      "family": "closed-form Joukowski ellipse",
      "n": 2048,
      "reference_n": 32768,
      "true_conformal_offset": 0.001,
      "monitor_h": 9.5367431640625e-07,
      "bgk_beta": 0.5825971579390108,
      "bgk_shift": 0.0005689425370498152,
      "correction_order": 4,
      "reference_value": 15.456635336324847,
      "raw_discrete_value": 15.466742661039932,
      "corrected_value": 15.456635336324727,
      "rel_error": 7.814913301043048e-15
    },
    {
      "shape": "golden_ellipse",
      "family": "closed-form Joukowski ellipse",
      "n": 2048,
      "reference_n": 32768,
      "true_conformal_offset": 0.001,
      "monitor_h": 9.5367431640625e-07,
      "bgk_beta": 0.5825971579390108,
      "bgk_shift": 0.0005689425370498152,
      "correction_order": 8,
      "reference_value": 15.456635336324847,
      "raw_discrete_value": 15.466742661039932,
      "corrected_value": 15.456635336324727,
      "rel_error": 7.814913301043048e-15
    },
    {
      "shape": "golden_ellipse",
      "family": "closed-form Joukowski ellipse",
      "n": 2048,
      "reference_n": 32768,
      "true_conformal_offset": 0.001,
      "monitor_h": 9.5367431640625e-07,
      "bgk_beta": 0.5825971579390108,
      "bgk_shift": 0.0005689425370498152,
      "correction_order": 16,
      "reference_value": 15.456635336324847,
      "raw_discrete_value": 15.466742661039932,
      "corrected_value": 15.456635336324727,
      "rel_error": 7.814913301043048e-15
    },
    {
      "shape": "golden_ellipse",
      "family": "closed-form Joukowski ellipse",
      "n": 2048,
      "reference_n": 32768,
      "true_conformal_offset": 0.001,
      "monitor_h": 2.384185791015625e-07,
      "bgk_beta": 0.5825971579390108,
      "bgk_shift": 0.0002844712685249076,
      "correction_order": 0,
      "reference_value": 15.456635336324847,
      "raw_discrete_value": 15.461689753867526,
      "corrected_value": 15.461689753867526,
      "rel_error": 0.0003270063265839322
    },
    {
      "shape": "golden_ellipse",
      "family": "closed-form Joukowski ellipse",
      "n": 2048,
      "reference_n": 32768,
      "true_conformal_offset": 0.001,
      "monitor_h": 2.384185791015625e-07,
      "bgk_beta": 0.5825971579390108,
      "bgk_shift": 0.0002844712685249076,
      "correction_order": 1,
      "reference_value": 15.456635336324847,
      "raw_discrete_value": 15.461689753867526,
      "corrected_value": 15.456636091636213,
      "rel_error": 4.886648025377838e-08
    },
    {
      "shape": "golden_ellipse",
      "family": "closed-form Joukowski ellipse",
      "n": 2048,
      "reference_n": 32768,
      "true_conformal_offset": 0.001,
      "monitor_h": 2.384185791015625e-07,
      "bgk_beta": 0.5825971579390108,
      "bgk_shift": 0.0002844712685249076,
      "correction_order": 2,
      "reference_value": 15.456635336324847,
      "raw_discrete_value": 15.461689753867526,
      "corrected_value": 15.456635336451063,
      "rel_error": 8.165779923220759e-12
    },
    {
      "shape": "golden_ellipse",
      "family": "closed-form Joukowski ellipse",
      "n": 2048,
      "reference_n": 32768,
      "true_conformal_offset": 0.001,
      "monitor_h": 2.384185791015625e-07,
      "bgk_beta": 0.5825971579390108,
      "bgk_shift": 0.0002844712685249076,
      "correction_order": 4,
      "reference_value": 15.456635336324847,
      "raw_discrete_value": 15.461689753867526,
      "corrected_value": 15.456635336324766,
      "rel_error": 5.2865589977644146e-15
    },
    {
      "shape": "golden_ellipse",
      "family": "closed-form Joukowski ellipse",
      "n": 2048,
      "reference_n": 32768,
      "true_conformal_offset": 0.001,
      "monitor_h": 2.384185791015625e-07,
      "bgk_beta": 0.5825971579390108,
      "bgk_shift": 0.0002844712685249076,
      "correction_order": 8,
      "reference_value": 15.456635336324847,
      "raw_discrete_value": 15.461689753867526,
      "corrected_value": 15.456635336324766,
      "rel_error": 5.2865589977644146e-15
    },
    {
      "shape": "golden_ellipse",
      "family": "closed-form Joukowski ellipse",
      "n": 2048,
      "reference_n": 32768,
      "true_conformal_offset": 0.001,
      "monitor_h": 2.384185791015625e-07,
      "bgk_beta": 0.5825971579390108,
      "bgk_shift": 0.0002844712685249076,
      "correction_order": 16,
      "reference_value": 15.456635336324847,
      "raw_discrete_value": 15.461689753867526,
      "corrected_value": 15.456635336324766,
      "rel_error": 5.2865589977644146e-15
    },
    {
      "shape": "golden_ellipse",
      "family": "closed-form Joukowski ellipse",
      "n": 2048,
      "reference_n": 32768,
      "true_conformal_offset": 0.001,
      "monitor_h": 5.960464477539063e-08,
      "bgk_beta": 0.5825971579390108,
      "bgk_shift": 0.0001422356342624538,
      "correction_order": 0,
      "reference_value": 15.456635336324847,
      "raw_discrete_value": 15.459162733939813,
      "corrected_value": 15.459162733939813,
      "rel_error": 0.00016351538093325487
    },
    {
      "shape": "golden_ellipse",
      "family": "closed-form Joukowski ellipse",
      "n": 2048,
      "reference_n": 32768,
      "true_conformal_offset": 0.001,
      "monitor_h": 5.960464477539063e-08,
      "bgk_beta": 0.5825971579390108,
      "bgk_shift": 0.0001422356342624538,
      "correction_order": 1,
      "reference_value": 15.456635336324847,
      "raw_discrete_value": 15.459162733939813,
      "corrected_value": 15.45663552518422,
      "rel_error": 1.2218660043129157e-08
    },
    {
      "shape": "golden_ellipse",
      "family": "closed-form Joukowski ellipse",
      "n": 2048,
      "reference_n": 32768,
      "true_conformal_offset": 0.001,
      "monitor_h": 5.960464477539063e-08,
      "bgk_beta": 0.5825971579390108,
      "bgk_shift": 0.0001422356342624538,
      "correction_order": 2,
      "reference_value": 15.456635336324847,
      "raw_discrete_value": 15.459162733939813,
      "corrected_value": 15.456635336340572,
      "rel_error": 1.0173178314828391e-12
    },
    {
      "shape": "golden_ellipse",
      "family": "closed-form Joukowski ellipse",
      "n": 2048,
      "reference_n": 32768,
      "true_conformal_offset": 0.001,
      "monitor_h": 5.960464477539063e-08,
      "bgk_beta": 0.5825971579390108,
      "bgk_shift": 0.0001422356342624538,
      "correction_order": 4,
      "reference_value": 15.456635336324847,
      "raw_discrete_value": 15.459162733939813,
      "corrected_value": 15.456635336324782,
      "rel_error": 4.2522322373322464e-15
    },
    {
      "shape": "golden_ellipse",
      "family": "closed-form Joukowski ellipse",
      "n": 2048,
      "reference_n": 32768,
      "true_conformal_offset": 0.001,
      "monitor_h": 5.960464477539063e-08,
      "bgk_beta": 0.5825971579390108,
      "bgk_shift": 0.0001422356342624538,
      "correction_order": 8,
      "reference_value": 15.456635336324847,
      "raw_discrete_value": 15.459162733939813,
      "corrected_value": 15.456635336324782,
      "rel_error": 4.2522322373322464e-15
    },
    {
      "shape": "golden_ellipse",
      "family": "closed-form Joukowski ellipse",
      "n": 2048,
      "reference_n": 32768,
      "true_conformal_offset": 0.001,
      "monitor_h": 5.960464477539063e-08,
      "bgk_beta": 0.5825971579390108,
      "bgk_shift": 0.0001422356342624538,
      "correction_order": 16,
      "reference_value": 15.456635336324847,
      "raw_discrete_value": 15.459162733939813,
      "corrected_value": 15.456635336324782,
      "rel_error": 4.2522322373322464e-15
    },
    {
      "shape": "golden_ellipse",
      "family": "closed-form Joukowski ellipse",
      "n": 2048,
      "reference_n": 32768,
      "true_conformal_offset": 0.001,
      "monitor_h": 1.4901161193847656e-08,
      "bgk_beta": 0.5825971579390108,
      "bgk_shift": 7.11178171312269e-05,
      "correction_order": 0,
      "reference_value": 15.456635336324847,
      "raw_discrete_value": 15.457899082349122,
      "corrected_value": 15.457899082349122,
      "rel_error": 8.176074525773988e-05
    },
    {
      "shape": "golden_ellipse",
      "family": "closed-form Joukowski ellipse",
      "n": 2048,
      "reference_n": 32768,
      "true_conformal_offset": 0.001,
      "monitor_h": 1.4901161193847656e-08,
      "bgk_beta": 0.5825971579390108,
      "bgk_shift": 7.11178171312269e-05,
      "correction_order": 1,
      "reference_value": 15.456635336324847,
      "raw_discrete_value": 15.457899082349122,
      "corrected_value": 15.456635383543581,
      "rel_error": 3.05491672569196e-09
    },
    {
      "shape": "golden_ellipse",
      "family": "closed-form Joukowski ellipse",
      "n": 2048,
      "reference_n": 32768,
      "true_conformal_offset": 0.001,
      "monitor_h": 1.4901161193847656e-08,
      "bgk_beta": 0.5825971579390108,
      "bgk_shift": 7.11178171312269e-05,
      "correction_order": 2,
      "reference_value": 15.456635336324847,
      "raw_discrete_value": 15.457899082349122,
      "corrected_value": 15.456635336326748,
      "rel_error": 1.2296995929582442e-13
    },
    {
      "shape": "golden_ellipse",
      "family": "closed-form Joukowski ellipse",
      "n": 2048,
      "reference_n": 32768,
      "true_conformal_offset": 0.001,
      "monitor_h": 1.4901161193847656e-08,
      "bgk_beta": 0.5825971579390108,
      "bgk_shift": 7.11178171312269e-05,
      "correction_order": 4,
      "reference_value": 15.456635336324847,
      "raw_discrete_value": 15.457899082349122,
      "corrected_value": 15.456635336324775,
      "rel_error": 4.711933019746543e-15
    },
    {
      "shape": "golden_ellipse",
      "family": "closed-form Joukowski ellipse",
      "n": 2048,
      "reference_n": 32768,
      "true_conformal_offset": 0.001,
      "monitor_h": 1.4901161193847656e-08,
      "bgk_beta": 0.5825971579390108,
      "bgk_shift": 7.11178171312269e-05,
      "correction_order": 8,
      "reference_value": 15.456635336324847,
      "raw_discrete_value": 15.457899082349122,
      "corrected_value": 15.456635336324775,
      "rel_error": 4.711933019746543e-15
    },
    {
      "shape": "golden_ellipse",
      "family": "closed-form Joukowski ellipse",
      "n": 2048,
      "reference_n": 32768,
      "true_conformal_offset": 0.001,
      "monitor_h": 1.4901161193847656e-08,
      "bgk_beta": 0.5825971579390108,
      "bgk_shift": 7.11178171312269e-05,
      "correction_order": 16,
      "reference_value": 15.456635336324847,
      "raw_discrete_value": 15.457899082349122,
      "corrected_value": 15.456635336324775,
      "rel_error": 4.711933019746543e-15
    },
    {
      "shape": "three_petal_laurent",
      "family": "smooth nonconvex finite Laurent map",
      "n": 2048,
      "reference_n": 32768,
      "true_conformal_offset": 0.001,
      "monitor_h": 1.52587890625e-05,
      "bgk_beta": 0.5825971579390108,
      "bgk_shift": 0.002275770148199261,
      "correction_order": 0,
      "reference_value": -0.596145205940274,
      "raw_discrete_value": -0.577145762866356,
      "corrected_value": -0.577145762866356,
      "rel_error": 0.03187049545077024
    },
    {
      "shape": "three_petal_laurent",
      "family": "smooth nonconvex finite Laurent map",
      "n": 2048,
      "reference_n": 32768,
      "true_conformal_offset": 0.001,
      "monitor_h": 1.52587890625e-05,
      "bgk_beta": 0.5825971579390108,
      "bgk_shift": 0.002275770148199261,
      "correction_order": 1,
      "reference_value": -0.596145205940274,
      "raw_discrete_value": -0.577145762866356,
      "corrected_value": -0.5961133462453909,
      "rel_error": 5.3442843397208966e-05
    },
    {
      "shape": "three_petal_laurent",
      "family": "smooth nonconvex finite Laurent map",
      "n": 2048,
      "reference_n": 32768,
      "true_conformal_offset": 0.001,
      "monitor_h": 1.52587890625e-05,
      "bgk_beta": 0.5825971579390108,
      "bgk_shift": 0.002275770148199261,
      "correction_order": 2,
      "reference_value": -0.596145205940274,
      "raw_discrete_value": -0.577145762866356,
      "corrected_value": -0.5961451314874514,
      "rel_error": 1.2489041567709712e-07
    },
    {
      "shape": "three_petal_laurent",
      "family": "smooth nonconvex finite Laurent map",
      "n": 2048,
      "reference_n": 32768,
      "true_conformal_offset": 0.001,
      "monitor_h": 1.52587890625e-05,
      "bgk_beta": 0.5825971579390108,
      "bgk_shift": 0.002275770148199261,
      "correction_order": 4,
      "reference_value": -0.596145205940274,
      "raw_discrete_value": -0.577145762866356,
      "corrected_value": -0.5961452059399505,
      "rel_error": 5.426848797106371e-13
    },
    {
      "shape": "three_petal_laurent",
      "family": "smooth nonconvex finite Laurent map",
      "n": 2048,
      "reference_n": 32768,
      "true_conformal_offset": 0.001,
      "monitor_h": 1.52587890625e-05,
      "bgk_beta": 0.5825971579390108,
      "bgk_shift": 0.002275770148199261,
      "correction_order": 8,
      "reference_value": -0.596145205940274,
      "raw_discrete_value": -0.577145762866356,
      "corrected_value": -0.5961452059402724,
      "rel_error": 2.6072712134347702e-15
    },
    {
      "shape": "three_petal_laurent",
      "family": "smooth nonconvex finite Laurent map",
      "n": 2048,
      "reference_n": 32768,
      "true_conformal_offset": 0.001,
      "monitor_h": 1.52587890625e-05,
      "bgk_beta": 0.5825971579390108,
      "bgk_shift": 0.002275770148199261,
      "correction_order": 16,
      "reference_value": -0.596145205940274,
      "raw_discrete_value": -0.577145762866356,
      "corrected_value": -0.5961452059402724,
      "rel_error": 2.6072712134347702e-15
    },
    {
      "shape": "three_petal_laurent",
      "family": "smooth nonconvex finite Laurent map",
      "n": 2048,
      "reference_n": 32768,
      "true_conformal_offset": 0.001,
      "monitor_h": 3.814697265625e-06,
      "bgk_beta": 0.5825971579390108,
      "bgk_shift": 0.0011378850740996304,
      "correction_order": 0,
      "reference_value": -0.596145205940274,
      "raw_discrete_value": -0.5866375101620448,
      "corrected_value": -0.5866375101620448,
      "rel_error": 0.015948624065898694
    },
    {
      "shape": "three_petal_laurent",
      "family": "smooth nonconvex finite Laurent map",
      "n": 2048,
      "reference_n": 32768,
      "true_conformal_offset": 0.001,
      "monitor_h": 3.814697265625e-06,
      "bgk_beta": 0.5825971579390108,
      "bgk_shift": 0.0011378850740996304,
      "correction_order": 1,
      "reference_value": -0.596145205940274,
      "raw_discrete_value": -0.5866375101620448,
      "corrected_value": -0.5961372223704973,
      "rel_error": 1.3391988557758936e-05
    },
    {
      "shape": "three_petal_laurent",
      "family": "smooth nonconvex finite Laurent map",
      "n": 2048,
      "reference_n": 32768,
      "true_conformal_offset": 0.001,
      "monitor_h": 3.814697265625e-06,
      "bgk_beta": 0.5825971579390108,
      "bgk_shift": 0.0011378850740996304,
      "correction_order": 2,
      "reference_value": -0.596145205940274,
      "raw_discrete_value": -0.5866375101620448,
      "corrected_value": -0.5961451966008001,
      "rel_error": 1.5666441276193493e-08
    },
    {
      "shape": "three_petal_laurent",
      "family": "smooth nonconvex finite Laurent map",
      "n": 2048,
      "reference_n": 32768,
      "true_conformal_offset": 0.001,
      "monitor_h": 3.814697265625e-06,
      "bgk_beta": 0.5825971579390108,
      "bgk_shift": 0.0011378850740996304,
      "correction_order": 4,
      "reference_value": -0.596145205940274,
      "raw_discrete_value": -0.5866375101620448,
      "corrected_value": -0.5961452059402624,
      "rel_error": 1.9368300442658294e-14
    },
    {
      "shape": "three_petal_laurent",
      "family": "smooth nonconvex finite Laurent map",
      "n": 2048,
      "reference_n": 32768,
      "true_conformal_offset": 0.001,
      "monitor_h": 3.814697265625e-06,
      "bgk_beta": 0.5825971579390108,
      "bgk_shift": 0.0011378850740996304,
      "correction_order": 8,
      "reference_value": -0.596145205940274,
      "raw_discrete_value": -0.5866375101620448,
      "corrected_value": -0.5961452059402725,
      "rel_error": 2.4210375553322868e-15
    },
    {
      "shape": "three_petal_laurent",
      "family": "smooth nonconvex finite Laurent map",
      "n": 2048,
      "reference_n": 32768,
      "true_conformal_offset": 0.001,
      "monitor_h": 3.814697265625e-06,
      "bgk_beta": 0.5825971579390108,
      "bgk_shift": 0.0011378850740996304,
      "correction_order": 16,
      "reference_value": -0.596145205940274,
      "raw_discrete_value": -0.5866375101620448,
      "corrected_value": -0.5961452059402725,
      "rel_error": 2.4210375553322868e-15
    },
    {
      "shape": "three_petal_laurent",
      "family": "smooth nonconvex finite Laurent map",
      "n": 2048,
      "reference_n": 32768,
      "true_conformal_offset": 0.001,
      "monitor_h": 9.5367431640625e-07,
      "bgk_beta": 0.5825971579390108,
      "bgk_shift": 0.0005689425370498152,
      "correction_order": 0,
      "reference_value": -0.596145205940274,
      "raw_discrete_value": -0.591389360990595,
      "corrected_value": -0.591389360990595,
      "rel_error": 0.00797766198954459
    },
    {
      "shape": "three_petal_laurent",
      "family": "smooth nonconvex finite Laurent map",
      "n": 2048,
      "reference_n": 32768,
      "true_conformal_offset": 0.001,
      "monitor_h": 9.5367431640625e-07,
      "bgk_beta": 0.5825971579390108,
      "bgk_shift": 0.0005689425370498152,
      "correction_order": 1,
      "reference_value": -0.596145205940274,
      "raw_discrete_value": -0.591389360990595,
      "corrected_value": -0.5961432077109018,
      "rel_error": 3.3519172045328157e-06
    },
    {
      "shape": "three_petal_laurent",
      "family": "smooth nonconvex finite Laurent map",
      "n": 2048,
      "reference_n": 32768,
      "true_conformal_offset": 0.001,
      "monitor_h": 9.5367431640625e-07,
      "bgk_beta": 0.5825971579390108,
      "bgk_shift": 0.0005689425370498152,
      "correction_order": 2,
      "reference_value": -0.596145205940274,
      "raw_discrete_value": -0.591389360990595,
      "corrected_value": -0.596145204770779,
      "rel_error": 1.961761889010641e-09
    },
    {
      "shape": "three_petal_laurent",
      "family": "smooth nonconvex finite Laurent map",
      "n": 2048,
      "reference_n": 32768,
      "true_conformal_offset": 0.001,
      "monitor_h": 9.5367431640625e-07,
      "bgk_beta": 0.5825971579390108,
      "bgk_shift": 0.0005689425370498152,
      "correction_order": 4,
      "reference_value": -0.596145205940274,
      "raw_discrete_value": -0.591389360990595,
      "corrected_value": -0.5961452059402728,
      "rel_error": 2.0485702391273195e-15
    },
    {
      "shape": "three_petal_laurent",
      "family": "smooth nonconvex finite Laurent map",
      "n": 2048,
      "reference_n": 32768,
      "true_conformal_offset": 0.001,
      "monitor_h": 9.5367431640625e-07,
      "bgk_beta": 0.5825971579390108,
      "bgk_shift": 0.0005689425370498152,
      "correction_order": 8,
      "reference_value": -0.596145205940274,
      "raw_discrete_value": -0.591389360990595,
      "corrected_value": -0.5961452059402731,
      "rel_error": 1.4898692648198688e-15
    },
    {
      "shape": "three_petal_laurent",
      "family": "smooth nonconvex finite Laurent map",
      "n": 2048,
      "reference_n": 32768,
      "true_conformal_offset": 0.001,
      "monitor_h": 9.5367431640625e-07,
      "bgk_beta": 0.5825971579390108,
      "bgk_shift": 0.0005689425370498152,
      "correction_order": 16,
      "reference_value": -0.596145205940274,
      "raw_discrete_value": -0.591389360990595,
      "corrected_value": -0.5961452059402731,
      "rel_error": 1.4898692648198688e-15
    },
    {
      "shape": "three_petal_laurent",
      "family": "smooth nonconvex finite Laurent map",
      "n": 2048,
      "reference_n": 32768,
      "true_conformal_offset": 0.001,
      "monitor_h": 2.384185791015625e-07,
      "bgk_beta": 0.5825971579390108,
      "bgk_shift": 0.0002844712685249076,
      "correction_order": 0,
      "reference_value": -0.596145205940274,
      "raw_discrete_value": -0.5937667837618623,
      "corrected_value": -0.5937667837618623,
      "rel_error": 0.003989669219364573
    },
    {
      "shape": "three_petal_laurent",
      "family": "smooth nonconvex finite Laurent map",
      "n": 2048,
      "reference_n": 32768,
      "true_conformal_offset": 0.001,
      "monitor_h": 2.384185791015625e-07,
      "bgk_beta": 0.5825971579390108,
      "bgk_shift": 0.0002844712685249076,
      "correction_order": 1,
      "reference_value": -0.596145205940274,
      "raw_discrete_value": -0.5937667837618623,
      "corrected_value": -0.5961447060904287,
      "rel_error": 8.384699571709158e-07
    },
    {
      "shape": "three_petal_laurent",
      "family": "smooth nonconvex finite Laurent map",
      "n": 2048,
      "reference_n": 32768,
      "true_conformal_offset": 0.001,
      "monitor_h": 2.384185791015625e-07,
      "bgk_beta": 0.5825971579390108,
      "bgk_shift": 0.0002844712685249076,
      "correction_order": 2,
      "reference_value": -0.596145205940274,
      "raw_discrete_value": -0.5937667837618623,
      "corrected_value": -0.5961452057939582,
      "rel_error": 2.4543640684497264e-10
    },
    {
      "shape": "three_petal_laurent",
      "family": "smooth nonconvex finite Laurent map",
      "n": 2048,
      "reference_n": 32768,
      "true_conformal_offset": 0.001,
      "monitor_h": 2.384185791015625e-07,
      "bgk_beta": 0.5825971579390108,
      "bgk_shift": 0.0002844712685249076,
      "correction_order": 4,
      "reference_value": -0.596145205940274,
      "raw_discrete_value": -0.5937667837618623,
      "corrected_value": -0.5961452059402739,
      "rel_error": 1.862336581024836e-16
    },
    {
      "shape": "three_petal_laurent",
      "family": "smooth nonconvex finite Laurent map",
      "n": 2048,
      "reference_n": 32768,
      "true_conformal_offset": 0.001,
      "monitor_h": 2.384185791015625e-07,
      "bgk_beta": 0.5825971579390108,
      "bgk_shift": 0.0002844712685249076,
      "correction_order": 8,
      "reference_value": -0.596145205940274,
      "raw_discrete_value": -0.5937667837618623,
      "corrected_value": -0.5961452059402739,
      "rel_error": 1.862336581024836e-16
    },
    {
      "shape": "three_petal_laurent",
      "family": "smooth nonconvex finite Laurent map",
      "n": 2048,
      "reference_n": 32768,
      "true_conformal_offset": 0.001,
      "monitor_h": 2.384185791015625e-07,
      "bgk_beta": 0.5825971579390108,
      "bgk_shift": 0.0002844712685249076,
      "correction_order": 16,
      "reference_value": -0.596145205940274,
      "raw_discrete_value": -0.5937667837618623,
      "corrected_value": -0.5961452059402739,
      "rel_error": 1.862336581024836e-16
    },
    {
      "shape": "three_petal_laurent",
      "family": "smooth nonconvex finite Laurent map",
      "n": 2048,
      "reference_n": 32768,
      "true_conformal_offset": 0.001,
      "monitor_h": 5.960464477539063e-08,
      "bgk_beta": 0.5825971579390108,
      "bgk_shift": 0.0001422356342624538,
      "correction_order": 0,
      "reference_value": -0.596145205940274,
      "raw_discrete_value": -0.5949558698703142,
      "corrected_value": -0.5949558698703142,
      "rel_error": 0.001995044257856368
    },
    {
      "shape": "three_petal_laurent",
      "family": "smooth nonconvex finite Laurent map",
      "n": 2048,
      "reference_n": 32768,
      "true_conformal_offset": 0.001,
      "monitor_h": 5.960464477539063e-08,
      "bgk_beta": 0.5825971579390108,
      "bgk_shift": 0.0001422356342624538,
      "correction_order": 1,
      "reference_value": -0.596145205940274,
      "raw_discrete_value": -0.5949558698703142,
      "corrected_value": -0.5961450809412252,
      "rel_error": 2.0967886268787345e-07
    },
    {
      "shape": "three_petal_laurent",
      "family": "smooth nonconvex finite Laurent map",
      "n": 2048,
      "reference_n": 32768,
      "true_conformal_offset": 0.001,
      "monitor_h": 5.960464477539063e-08,
      "bgk_beta": 0.5825971579390108,
      "bgk_shift": 0.0001422356342624538,
      "correction_order": 2,
      "reference_value": -0.596145205940274,
      "raw_discrete_value": -0.5949558698703142,
      "corrected_value": -0.596145205921976,
      "rel_error": 3.069391412650273e-11
    },
    {
      "shape": "three_petal_laurent",
      "family": "smooth nonconvex finite Laurent map",
      "n": 2048,
      "reference_n": 32768,
      "true_conformal_offset": 0.001,
      "monitor_h": 5.960464477539063e-08,
      "bgk_beta": 0.5825971579390108,
      "bgk_shift": 0.0001422356342624538,
      "correction_order": 4,
      "reference_value": -0.596145205940274,
      "raw_discrete_value": -0.5949558698703142,
      "corrected_value": -0.5961452059402734,
      "rel_error": 9.31168290512418e-16
    },
    {
      "shape": "three_petal_laurent",
      "family": "smooth nonconvex finite Laurent map",
      "n": 2048,
      "reference_n": 32768,
      "true_conformal_offset": 0.001,
      "monitor_h": 5.960464477539063e-08,
      "bgk_beta": 0.5825971579390108,
      "bgk_shift": 0.0001422356342624538,
      "correction_order": 8,
      "reference_value": -0.596145205940274,
      "raw_discrete_value": -0.5949558698703142,
      "corrected_value": -0.5961452059402734,
      "rel_error": 9.31168290512418e-16
    },
    {
      "shape": "three_petal_laurent",
      "family": "smooth nonconvex finite Laurent map",
      "n": 2048,
      "reference_n": 32768,
      "true_conformal_offset": 0.001,
      "monitor_h": 5.960464477539063e-08,
      "bgk_beta": 0.5825971579390108,
      "bgk_shift": 0.0001422356342624538,
      "correction_order": 16,
      "reference_value": -0.596145205940274,
      "raw_discrete_value": -0.5949558698703142,
      "corrected_value": -0.5961452059402734,
      "rel_error": 9.31168290512418e-16
    },
    {
      "shape": "three_petal_laurent",
      "family": "smooth nonconvex finite Laurent map",
      "n": 2048,
      "reference_n": 32768,
      "true_conformal_offset": 0.001,
      "monitor_h": 1.4901161193847656e-08,
      "bgk_beta": 0.5825971579390108,
      "bgk_shift": 7.11178171312269e-05,
      "correction_order": 0,
      "reference_value": -0.596145205940274,
      "raw_discrete_value": -0.5955505066532434,
      "corrected_value": -0.5955505066532434,
      "rel_error": 0.0009975745524827368
    },
    {
      "shape": "three_petal_laurent",
      "family": "smooth nonconvex finite Laurent map",
      "n": 2048,
      "reference_n": 32768,
      "true_conformal_offset": 0.001,
      "monitor_h": 1.4901161193847656e-08,
      "bgk_beta": 0.5825971579390108,
      "bgk_shift": 7.11178171312269e-05,
      "correction_order": 1,
      "reference_value": -0.596145205940274,
      "raw_discrete_value": -0.5955505066532434,
      "corrected_value": -0.5961451746859355,
      "rel_error": 5.24273920836801e-08
    },
    {
      "shape": "three_petal_laurent",
      "family": "smooth nonconvex finite Laurent map",
      "n": 2048,
      "reference_n": 32768,
      "true_conformal_offset": 0.001,
      "monitor_h": 1.4901161193847656e-08,
      "bgk_beta": 0.5825971579390108,
      "bgk_shift": 7.11178171312269e-05,
      "correction_order": 2,
      "reference_value": -0.596145205940274,
      "raw_discrete_value": -0.5955505066532434,
      "corrected_value": -0.5961452059379847,
      "rel_error": 3.840138030073211e-12
    },
    {
      "shape": "three_petal_laurent",
      "family": "smooth nonconvex finite Laurent map",
      "n": 2048,
      "reference_n": 32768,
      "true_conformal_offset": 0.001,
      "monitor_h": 1.4901161193847656e-08,
      "bgk_beta": 0.5825971579390108,
      "bgk_shift": 7.11178171312269e-05,
      "correction_order": 4,
      "reference_value": -0.596145205940274,
      "raw_discrete_value": -0.5955505066532434,
      "corrected_value": -0.5961452059402724,
      "rel_error": 2.6072712134347702e-15
    },
    {
      "shape": "three_petal_laurent",
      "family": "smooth nonconvex finite Laurent map",
      "n": 2048,
      "reference_n": 32768,
      "true_conformal_offset": 0.001,
      "monitor_h": 1.4901161193847656e-08,
      "bgk_beta": 0.5825971579390108,
      "bgk_shift": 7.11178171312269e-05,
      "correction_order": 8,
      "reference_value": -0.596145205940274,
      "raw_discrete_value": -0.5955505066532434,
      "corrected_value": -0.5961452059402724,
      "rel_error": 2.6072712134347702e-15
    },
    {
      "shape": "three_petal_laurent",
      "family": "smooth nonconvex finite Laurent map",
      "n": 2048,
      "reference_n": 32768,
      "true_conformal_offset": 0.001,
      "monitor_h": 1.4901161193847656e-08,
      "bgk_beta": 0.5825971579390108,
      "bgk_shift": 7.11178171312269e-05,
      "correction_order": 16,
      "reference_value": -0.596145205940274,
      "raw_discrete_value": -0.5955505066532434,
      "corrected_value": -0.5961452059402724,
      "rel_error": 2.6072712134347702e-15
    },
    {
      "shape": "perturbed_ellipse",
      "family": "smooth anisotropic finite Laurent map",
      "n": 2048,
      "reference_n": 32768,
      "true_conformal_offset": 0.001,
      "monitor_h": 1.52587890625e-05,
      "bgk_beta": 0.5825971579390108,
      "bgk_shift": 0.002275770148199261,
      "correction_order": 0,
      "reference_value": 1.0422622791870901,
      "raw_discrete_value": 1.0618402756643162,
      "corrected_value": 1.0618402756643162,
      "rel_error": 0.018784136074171114
    },
    {
      "shape": "perturbed_ellipse",
      "family": "smooth anisotropic finite Laurent map",
      "n": 2048,
      "reference_n": 32768,
      "true_conformal_offset": 0.001,
      "monitor_h": 1.52587890625e-05,
      "bgk_beta": 0.5825971579390108,
      "bgk_shift": 0.002275770148199261,
      "correction_order": 1,
      "reference_value": 1.0422622791870901,
      "raw_discrete_value": 1.0618402756643162,
      "corrected_value": 1.042291215572414,
      "rel_error": 2.77630553284843e-05
    },
    {
      "shape": "perturbed_ellipse",
      "family": "smooth anisotropic finite Laurent map",
      "n": 2048,
      "reference_n": 32768,
      "true_conformal_offset": 0.001,
      "monitor_h": 1.52587890625e-05,
      "bgk_beta": 0.5825971579390108,
      "bgk_shift": 0.002275770148199261,
      "correction_order": 2,
      "reference_value": 1.0422622791870901,
      "raw_discrete_value": 1.0618402756643162,
      "corrected_value": 1.042262340061691,
      "rel_error": 5.840622090163151e-08
    },
    {
      "shape": "perturbed_ellipse",
      "family": "smooth anisotropic finite Laurent map",
      "n": 2048,
      "reference_n": 32768,
      "true_conformal_offset": 0.001,
      "monitor_h": 1.52587890625e-05,
      "bgk_beta": 0.5825971579390108,
      "bgk_shift": 0.002275770148199261,
      "correction_order": 4,
      "reference_value": 1.0422622791870901,
      "raw_discrete_value": 1.0618402756643162,
      "corrected_value": 1.0422622791873215,
      "rel_error": 2.2198872870304723e-13
    },
    {
      "shape": "perturbed_ellipse",
      "family": "smooth anisotropic finite Laurent map",
      "n": 2048,
      "reference_n": 32768,
      "true_conformal_offset": 0.001,
      "monitor_h": 1.52587890625e-05,
      "bgk_beta": 0.5825971579390108,
      "bgk_shift": 0.002275770148199261,
      "correction_order": 8,
      "reference_value": 1.0422622791870901,
      "raw_discrete_value": 1.0618402756643162,
      "corrected_value": 1.0422622791870944,
      "rel_error": 4.04777912222447e-15
    },
    {
      "shape": "perturbed_ellipse",
      "family": "smooth anisotropic finite Laurent map",
      "n": 2048,
      "reference_n": 32768,
      "true_conformal_offset": 0.001,
      "monitor_h": 1.52587890625e-05,
      "bgk_beta": 0.5825971579390108,
      "bgk_shift": 0.002275770148199261,
      "correction_order": 16,
      "reference_value": 1.0422622791870901,
      "raw_discrete_value": 1.0618402756643162,
      "corrected_value": 1.0422622791870944,
      "rel_error": 4.04777912222447e-15
    },
    {
      "shape": "perturbed_ellipse",
      "family": "smooth anisotropic finite Laurent map",
      "n": 2048,
      "reference_n": 32768,
      "true_conformal_offset": 0.001,
      "monitor_h": 3.814697265625e-06,
      "bgk_beta": 0.5825971579390108,
      "bgk_shift": 0.0011378850740996304,
      "correction_order": 0,
      "reference_value": 1.0422622791870901,
      "raw_discrete_value": 1.0520585191396838,
      "corrected_value": 1.0520585191396838,
      "rel_error": 0.009399016109682357
    },
    {
      "shape": "perturbed_ellipse",
      "family": "smooth anisotropic finite Laurent map",
      "n": 2048,
      "reference_n": 32768,
      "true_conformal_offset": 0.001,
      "monitor_h": 3.814697265625e-06,
      "bgk_beta": 0.5825971579390108,
      "bgk_shift": 0.0011378850740996304,
      "correction_order": 1,
      "reference_value": 1.0422622791870901,
      "raw_discrete_value": 1.0520585191396838,
      "corrected_value": 1.0422695285270598,
      "rel_error": 6.9553893625552645e-06
    },
    {
      "shape": "perturbed_ellipse",
      "family": "smooth anisotropic finite Laurent map",
      "n": 2048,
      "reference_n": 32768,
      "true_conformal_offset": 0.001,
      "monitor_h": 3.814697265625e-06,
      "bgk_beta": 0.5825971579390108,
      "bgk_shift": 0.0011378850740996304,
      "correction_order": 2,
      "reference_value": 1.0422622791870901,
      "raw_discrete_value": 1.0520585191396838,
      "corrected_value": 1.0422622868214195,
      "rel_error": 7.3247680006575895e-09
    },
    {
      "shape": "perturbed_ellipse",
      "family": "smooth anisotropic finite Laurent map",
      "n": 2048,
      "reference_n": 32768,
      "true_conformal_offset": 0.001,
      "monitor_h": 3.814697265625e-06,
      "bgk_beta": 0.5825971579390108,
      "bgk_shift": 0.0011378850740996304,
      "correction_order": 4,
      "reference_value": 1.0422622791870901,
      "raw_discrete_value": 1.0520585191396838,
      "corrected_value": 1.042262279187098,
      "rel_error": 7.456435225150339e-15
    },
    {
      "shape": "perturbed_ellipse",
      "family": "smooth anisotropic finite Laurent map",
      "n": 2048,
      "reference_n": 32768,
      "true_conformal_offset": 0.001,
      "monitor_h": 3.814697265625e-06,
      "bgk_beta": 0.5825971579390108,
      "bgk_shift": 0.0011378850740996304,
      "correction_order": 8,
      "reference_value": 1.0422622791870901,
      "raw_discrete_value": 1.0520585191396838,
      "corrected_value": 1.0422622791870908,
      "rel_error": 6.391230192986005e-16
    },
    {
      "shape": "perturbed_ellipse",
      "family": "smooth anisotropic finite Laurent map",
      "n": 2048,
      "reference_n": 32768,
      "true_conformal_offset": 0.001,
      "monitor_h": 3.814697265625e-06,
      "bgk_beta": 0.5825971579390108,
      "bgk_shift": 0.0011378850740996304,
      "correction_order": 16,
      "reference_value": 1.0422622791870901,
      "raw_discrete_value": 1.0520585191396838,
      "corrected_value": 1.0422622791870908,
      "rel_error": 6.391230192986005e-16
    },
    {
      "shape": "perturbed_ellipse",
      "family": "smooth anisotropic finite Laurent map",
      "n": 2048,
      "reference_n": 32768,
      "true_conformal_offset": 0.001,
      "monitor_h": 9.5367431640625e-07,
      "bgk_beta": 0.5825971579390108,
      "bgk_shift": 0.0005689425370498152,
      "correction_order": 0,
      "reference_value": 1.0422622791870901,
      "raw_discrete_value": 1.047162212453192,
      "corrected_value": 1.047162212453192,
      "rel_error": 0.0047012478182781705
    },
    {
      "shape": "perturbed_ellipse",
      "family": "smooth anisotropic finite Laurent map",
      "n": 2048,
      "reference_n": 32768,
      "true_conformal_offset": 0.001,
      "monitor_h": 9.5367431640625e-07,
      "bgk_beta": 0.5825971579390108,
      "bgk_shift": 0.0005689425370498152,
      "correction_order": 1,
      "reference_value": 1.0422622791870901,
      "raw_discrete_value": 1.047162212453192,
      "corrected_value": 1.042264093432231,
      "rel_error": 1.7406800351639388e-06
    },
    {
      "shape": "perturbed_ellipse",
      "family": "smooth anisotropic finite Laurent map",
      "n": 2048,
      "reference_n": 32768,
      "true_conformal_offset": 0.001,
      "monitor_h": 9.5367431640625e-07,
      "bgk_beta": 0.5825971579390108,
      "bgk_shift": 0.0005689425370498152,
      "correction_order": 2,
      "reference_value": 1.0422622791870901,
      "raw_discrete_value": 1.047162212453192,
      "corrected_value": 1.042262280142948,
      "rel_error": 9.170991375332115e-10
    },
    {
      "shape": "perturbed_ellipse",
      "family": "smooth anisotropic finite Laurent map",
      "n": 2048,
      "reference_n": 32768,
      "true_conformal_offset": 0.001,
      "monitor_h": 9.5367431640625e-07,
      "bgk_beta": 0.5825971579390108,
      "bgk_shift": 0.0005689425370498152,
      "correction_order": 4,
      "reference_value": 1.0422622791870901,
      "raw_discrete_value": 1.047162212453192,
      "corrected_value": 1.0422622791870904,
      "rel_error": 2.1304100643286683e-16
    },
    {
      "shape": "perturbed_ellipse",
      "family": "smooth anisotropic finite Laurent map",
      "n": 2048,
      "reference_n": 32768,
      "true_conformal_offset": 0.001,
      "monitor_h": 9.5367431640625e-07,
      "bgk_beta": 0.5825971579390108,
      "bgk_shift": 0.0005689425370498152,
      "correction_order": 8,
      "reference_value": 1.0422622791870901,
      "raw_discrete_value": 1.047162212453192,
      "corrected_value": 1.0422622791870901,
      "rel_error": 0.0
    },
    {
      "shape": "perturbed_ellipse",
      "family": "smooth anisotropic finite Laurent map",
      "n": 2048,
      "reference_n": 32768,
      "true_conformal_offset": 0.001,
      "monitor_h": 9.5367431640625e-07,
      "bgk_beta": 0.5825971579390108,
      "bgk_shift": 0.0005689425370498152,
      "correction_order": 16,
      "reference_value": 1.0422622791870901,
      "raw_discrete_value": 1.047162212453192,
      "corrected_value": 1.0422622791870901,
      "rel_error": 0.0
    },
    {
      "shape": "perturbed_ellipse",
      "family": "smooth anisotropic finite Laurent map",
      "n": 2048,
      "reference_n": 32768,
      "true_conformal_offset": 0.001,
      "monitor_h": 2.384185791015625e-07,
      "bgk_beta": 0.5825971579390108,
      "bgk_shift": 0.0002844712685249076,
      "correction_order": 0,
      "reference_value": 1.0422622791870901,
      "raw_discrete_value": 1.0447126995009406,
      "corrected_value": 1.0447126995009406,
      "rel_error": 0.0023510591938160266
    },
    {
      "shape": "perturbed_ellipse",
      "family": "smooth anisotropic finite Laurent map",
      "n": 2048,
      "reference_n": 32768,
      "true_conformal_offset": 0.001,
      "monitor_h": 2.384185791015625e-07,
      "bgk_beta": 0.5825971579390108,
      "bgk_shift": 0.0002844712685249076,
      "correction_order": 1,
      "reference_value": 1.0422622791870901,
      "raw_discrete_value": 1.0447126995009406,
      "corrected_value": 1.0422627329874372,
      "rel_error": 4.3539937704710955e-07
    },
    {
      "shape": "perturbed_ellipse",
      "family": "smooth anisotropic finite Laurent map",
      "n": 2048,
      "reference_n": 32768,
      "true_conformal_offset": 0.001,
      "monitor_h": 2.384185791015625e-07,
      "bgk_beta": 0.5825971579390108,
      "bgk_shift": 0.0002844712685249076,
      "correction_order": 2,
      "reference_value": 1.0422622791870901,
      "raw_discrete_value": 1.0447126995009406,
      "corrected_value": 1.0422622793066698,
      "rel_error": 1.1473089056334966e-10
    },
    {
      "shape": "perturbed_ellipse",
      "family": "smooth anisotropic finite Laurent map",
      "n": 2048,
      "reference_n": 32768,
      "true_conformal_offset": 0.001,
      "monitor_h": 2.384185791015625e-07,
      "bgk_beta": 0.5825971579390108,
      "bgk_shift": 0.0002844712685249076,
      "correction_order": 4,
      "reference_value": 1.0422622791870901,
      "raw_discrete_value": 1.0447126995009406,
      "corrected_value": 1.0422622791870895,
      "rel_error": 6.391230192986005e-16
    },
    {
      "shape": "perturbed_ellipse",
      "family": "smooth anisotropic finite Laurent map",
      "n": 2048,
      "reference_n": 32768,
      "true_conformal_offset": 0.001,
      "monitor_h": 2.384185791015625e-07,
      "bgk_beta": 0.5825971579390108,
      "bgk_shift": 0.0002844712685249076,
      "correction_order": 8,
      "reference_value": 1.0422622791870901,
      "raw_discrete_value": 1.0447126995009406,
      "corrected_value": 1.0422622791870895,
      "rel_error": 6.391230192986005e-16
    },
    {
      "shape": "perturbed_ellipse",
      "family": "smooth anisotropic finite Laurent map",
      "n": 2048,
      "reference_n": 32768,
      "true_conformal_offset": 0.001,
      "monitor_h": 2.384185791015625e-07,
      "bgk_beta": 0.5825971579390108,
      "bgk_shift": 0.0002844712685249076,
      "correction_order": 16,
      "reference_value": 1.0422622791870901,
      "raw_discrete_value": 1.0447126995009406,
      "corrected_value": 1.0422622791870895,
      "rel_error": 6.391230192986005e-16
    },
    {
      "shape": "perturbed_ellipse",
      "family": "smooth anisotropic finite Laurent map",
      "n": 2048,
      "reference_n": 32768,
      "true_conformal_offset": 0.001,
      "monitor_h": 5.960464477539063e-08,
      "bgk_beta": 0.5825971579390108,
      "bgk_shift": 0.0001422356342624538,
      "correction_order": 0,
      "reference_value": 1.0422622791870901,
      "raw_discrete_value": 1.0434876028090485,
      "corrected_value": 1.0434876028090485,
      "rel_error": 0.0011756384610925978
    },
    {
      "shape": "perturbed_ellipse",
      "family": "smooth anisotropic finite Laurent map",
      "n": 2048,
      "reference_n": 32768,
      "true_conformal_offset": 0.001,
      "monitor_h": 5.960464477539063e-08,
      "bgk_beta": 0.5825971579390108,
      "bgk_shift": 0.0001422356342624538,
      "correction_order": 1,
      "reference_value": 1.0422622791870901,
      "raw_discrete_value": 1.0434876028090485,
      "corrected_value": 1.0422623926670747,
      "rel_error": 1.0887852970069106e-07
    },
    {
      "shape": "perturbed_ellipse",
      "family": "smooth anisotropic finite Laurent map",
      "n": 2048,
      "reference_n": 32768,
      "true_conformal_offset": 0.001,
      "monitor_h": 5.960464477539063e-08,
      "bgk_beta": 0.5825971579390108,
      "bgk_shift": 0.0001422356342624538,
      "correction_order": 2,
      "reference_value": 1.0422622791870901,
      "raw_discrete_value": 1.0434876028090485,
      "corrected_value": 1.0422622792020402,
      "rel_error": 1.4343837922118491e-11
    },
    {
      "shape": "perturbed_ellipse",
      "family": "smooth anisotropic finite Laurent map",
      "n": 2048,
      "reference_n": 32768,
      "true_conformal_offset": 0.001,
      "monitor_h": 5.960464477539063e-08,
      "bgk_beta": 0.5825971579390108,
      "bgk_shift": 0.0001422356342624538,
      "correction_order": 4,
      "reference_value": 1.0422622791870901,
      "raw_discrete_value": 1.0434876028090485,
      "corrected_value": 1.0422622791870864,
      "rel_error": 3.621697109358736e-15
    },
    {
      "shape": "perturbed_ellipse",
      "family": "smooth anisotropic finite Laurent map",
      "n": 2048,
      "reference_n": 32768,
      "true_conformal_offset": 0.001,
      "monitor_h": 5.960464477539063e-08,
      "bgk_beta": 0.5825971579390108,
      "bgk_shift": 0.0001422356342624538,
      "correction_order": 8,
      "reference_value": 1.0422622791870901,
      "raw_discrete_value": 1.0434876028090485,
      "corrected_value": 1.0422622791870864,
      "rel_error": 3.621697109358736e-15
    },
    {
      "shape": "perturbed_ellipse",
      "family": "smooth anisotropic finite Laurent map",
      "n": 2048,
      "reference_n": 32768,
      "true_conformal_offset": 0.001,
      "monitor_h": 5.960464477539063e-08,
      "bgk_beta": 0.5825971579390108,
      "bgk_shift": 0.0001422356342624538,
      "correction_order": 16,
      "reference_value": 1.0422622791870901,
      "raw_discrete_value": 1.0434876028090485,
      "corrected_value": 1.0422622791870864,
      "rel_error": 3.621697109358736e-15
    },
    {
      "shape": "perturbed_ellipse",
      "family": "smooth anisotropic finite Laurent map",
      "n": 2048,
      "reference_n": 32768,
      "true_conformal_offset": 0.001,
      "monitor_h": 1.4901161193847656e-08,
      "bgk_beta": 0.5825971579390108,
      "bgk_shift": 7.11178171312269e-05,
      "correction_order": 0,
      "reference_value": 1.0422622791870901,
      "raw_discrete_value": 1.042874969369938,
      "corrected_value": 1.042874969369938,
      "rel_error": 0.0005878464519752988
    },
    {
      "shape": "perturbed_ellipse",
      "family": "smooth anisotropic finite Laurent map",
      "n": 2048,
      "reference_n": 32768,
      "true_conformal_offset": 0.001,
      "monitor_h": 1.4901161193847656e-08,
      "bgk_beta": 0.5825971579390108,
      "bgk_shift": 7.11178171312269e-05,
      "correction_order": 1,
      "reference_value": 1.0422622791870901,
      "raw_discrete_value": 1.042874969369938,
      "corrected_value": 1.0422623075608264,
      "rel_error": 2.722322088788512e-08
    },
    {
      "shape": "perturbed_ellipse",
      "family": "smooth anisotropic finite Laurent map",
      "n": 2048,
      "reference_n": 32768,
      "true_conformal_offset": 0.001,
      "monitor_h": 1.4901161193847656e-08,
      "bgk_beta": 0.5825971579390108,
      "bgk_shift": 7.11178171312269e-05,
      "correction_order": 2,
      "reference_value": 1.0422622791870901,
      "raw_discrete_value": 1.042874969369938,
      "corrected_value": 1.0422622791889602,
      "rel_error": 1.7942313561776044e-12
    },
    {
      "shape": "perturbed_ellipse",
      "family": "smooth anisotropic finite Laurent map",
      "n": 2048,
      "reference_n": 32768,
      "true_conformal_offset": 0.001,
      "monitor_h": 1.4901161193847656e-08,
      "bgk_beta": 0.5825971579390108,
      "bgk_shift": 7.11178171312269e-05,
      "correction_order": 4,
      "reference_value": 1.0422622791870901,
      "raw_discrete_value": 1.042874969369938,
      "corrected_value": 1.0422622791870906,
      "rel_error": 4.2608201286573366e-16
    },
    {
      "shape": "perturbed_ellipse",
      "family": "smooth anisotropic finite Laurent map",
      "n": 2048,
      "reference_n": 32768,
      "true_conformal_offset": 0.001,
      "monitor_h": 1.4901161193847656e-08,
      "bgk_beta": 0.5825971579390108,
      "bgk_shift": 7.11178171312269e-05,
      "correction_order": 8,
      "reference_value": 1.0422622791870901,
      "raw_discrete_value": 1.042874969369938,
      "corrected_value": 1.0422622791870906,
      "rel_error": 4.2608201286573366e-16
    },
    {
      "shape": "perturbed_ellipse",
      "family": "smooth anisotropic finite Laurent map",
      "n": 2048,
      "reference_n": 32768,
      "true_conformal_offset": 0.001,
      "monitor_h": 1.4901161193847656e-08,
      "bgk_beta": 0.5825971579390108,
      "bgk_shift": 7.11178171312269e-05,
      "correction_order": 16,
      "reference_value": 1.0422622791870901,
      "raw_discrete_value": 1.042874969369938,
      "corrected_value": 1.0422622791870906,
      "rel_error": 4.2608201286573366e-16
    }
  ],
  "summary": [
    {
      "shape": "circle",
      "raw_error_power_in_h": 0.49994082130324896,
      "order1_power_in_h": 0.999885611570988,
      "order2_power_in_h": 1.4999458836668493,
      "finest_h": 1.4901161193847656e-08,
      "finest_bgk_shift": 7.11178171312269e-05,
      "finest_raw_rel_error": 0.001700625569780076,
      "finest_order1_rel_error": 6.06667051438821e-08,
      "finest_order2_rel_error": 2.0917512760088633e-12,
      "finest_order4_rel_error": 1.3454248766022276e-15,
      "finest_order8_rel_error": 1.3454248766022276e-15
    },
    {
      "shape": "golden_ellipse",
      "raw_error_power_in_h": 0.4999380188200446,
      "order1_power_in_h": 0.9998616302654381,
      "order2_power_in_h": 1.5082922177596292,
      "finest_h": 1.4901161193847656e-08,
      "finest_bgk_shift": 7.11178171312269e-05,
      "finest_raw_rel_error": 8.176074525773988e-05,
      "finest_order1_rel_error": 3.05491672569196e-09,
      "finest_order2_rel_error": 1.2296995929582442e-13,
      "finest_order4_rel_error": 4.711933019746543e-15,
      "finest_order8_rel_error": 4.711933019746543e-15
    },
    {
      "shape": "three_petal_laurent",
      "raw_error_power_in_h": 0.4999128338304955,
      "order1_power_in_h": 0.9997571709702052,
      "order2_power_in_h": 1.4994826455152093,
      "finest_h": 1.4901161193847656e-08,
      "finest_bgk_shift": 7.11178171312269e-05,
      "finest_raw_rel_error": 0.0009975745524827368,
      "finest_order1_rel_error": 5.24273920836801e-08,
      "finest_order2_rel_error": 3.840138030073211e-12,
      "finest_order4_rel_error": 2.6072712134347702e-15,
      "finest_order8_rel_error": 2.6072712134347702e-15
    },
    {
      "shape": "perturbed_ellipse",
      "raw_error_power_in_h": 0.4999231890876725,
      "order1_power_in_h": 0.9997814114884639,
      "order2_power_in_h": 1.4996227375948168,
      "finest_h": 1.4901161193847656e-08,
      "finest_bgk_shift": 7.11178171312269e-05,
      "finest_raw_rel_error": 0.0005878464519752988,
      "finest_order1_rel_error": 2.722322088788512e-08,
      "finest_order2_rel_error": 1.7942313561776044e-12,
      "finest_order4_rel_error": 4.2608201286573366e-16,
      "finest_order8_rel_error": 4.2608201286573366e-16
    }
  ]
}