{
  "all_cycle_cases_pass": true,
  "bgk_constant": 0.5825971579390107,
  "certificate": "beta_counterterm",
  "cycle_rows": {
    "s=1/2": [
      {
        "after_j1_abs": 1.1640727140125265e-06,
        "after_j2_abs": 2.5472455440395513e-09,
        "beta_only_error_abs": 0.001625275205349595,
        "bulk_abs": 35.54306350526693,
        "label": "s=1/2",
        "n": 128,
        "raw_abs": 32.620729212442406,
        "rung1_ratio_abs_error": 0.0007167444952633796,
        "rung1_ratio_im": 0.0,
        "rung1_ratio_re": 1.0007167444952634
      },
      {
        "after_j1_abs": 2.913371454852009e-07,
        "after_j2_abs": 3.178444039406194e-10,
        "beta_only_error_abs": 0.0008123469034632764,
        "bulk_abs": 50.26548245743669,
        "label": "s=1/2",
        "n": 256,
        "raw_abs": 47.34396109291406,
        "rung1_ratio_abs_error": 0.00035876503723291823,
        "rung1_ratio_im": 0.0,
        "rung1_ratio_re": 1.000358765037233
      },
      {
        "after_j1_abs": 7.287405213349746e-08,
        "after_j2_abs": 3.969533878791647e-11,
        "beta_only_error_abs": 0.00040610065721102915,
        "bulk_abs": 71.08612701053386,
        "label": "s=1/2",
        "n": 512,
        "raw_abs": 68.16501189225748,
        "rung1_ratio_abs_error": 0.000179480457141473,
        "rung1_ratio_im": 0.0,
        "rung1_ratio_re": 1.0001794804571416
      },
      {
        "after_j1_abs": 1.822347715553082e-08,
        "after_j2_abs": 4.9597125405247094e-12,
        "beta_only_error_abs": 0.00020303211505660334,
        "bulk_abs": 100.53096491487338,
        "label": "s=1/2",
        "n": 1024,
        "raw_abs": 97.61005286513915,
        "rung1_ratio_abs_error": 8.976468070116872e-05,
        "rung1_ratio_im": 0.0,
        "rung1_ratio_re": 1.0000897646807012
      },
      {
        "after_j1_abs": 4.556489390877816e-09,
        "after_j2_abs": 6.198261400201662e-13,
        "beta_only_error_abs": 0.00010151150227911478,
        "bulk_abs": 142.17225402106772,
        "label": "s=1/2",
        "n": 2048,
        "raw_abs": 139.25144349194628,
        "rung1_ratio_abs_error": 4.488844931180161e-05,
        "rung1_ratio_im": 0.0,
        "rung1_ratio_re": 1.0000448884493118
      },
      {
        "after_j1_abs": 1.139199834611393e-09,
        "after_j2_abs": 7.746964306603478e-14,
        "beta_only_error_abs": 5.0754612094696565e-05,
        "bulk_abs": 201.06192982974676,
        "label": "s=1/2",
        "n": 4096,
        "raw_abs": 198.1411700575155,
        "rung1_ratio_abs_error": 2.244575138673358e-05,
        "rung1_ratio_im": 0.0,
        "rung1_ratio_re": 1.0000224457513867
      },
      {
        "after_j1_abs": 2.8480964289738256e-10,
        "after_j2_abs": 9.683166232154539e-15,
        "beta_only_error_abs": 2.5377021257073875e-05,
        "bulk_abs": 284.34450804213543,
        "label": "s=1/2",
        "n": 8192,
        "raw_abs": 281.423773647495,
        "rung1_ratio_abs_error": 1.122325731235686e-05,
        "rung1_ratio_im": 0.0,
        "rung1_ratio_re": 1.0000112232573124
      }
    ],
    "s=1/2+0.3i": [
      {
        "after_j1_abs": 1.6225559480919922e-06,
        "after_j2_abs": 3.635385727733329e-09,
        "beta_only_error_abs": 0.0019077997624394722,
        "bulk_abs": 31.41694670773535,
        "label": "s=1/2+0.3i",
        "n": 128,
        "raw_abs": 31.143397776165653,
        "rung1_ratio_abs_error": 0.0008511132490163517,
        "rung1_ratio_im": 0.0004238464498249548,
        "rung1_ratio_re": 1.0007380704232132
      },
      {
        "after_j1_abs": 4.0592901782933093e-07,
        "after_j2_abs": 4.538656661923942e-10,
        "beta_only_error_abs": 0.0009535484800547459,
        "bulk_abs": 44.430272122432086,
        "label": "s=1/2+0.3i",
        "n": 256,
        "raw_abs": 44.65264882837208,
        "rung1_ratio_abs_error": 0.00042586089637280163,
        "rung1_ratio_im": 0.00021175563253169778,
        "rung1_ratio_re": 1.0003694821445626
      },
      {
        "after_j1_abs": 1.015183848989088e-07,
        "after_j2_abs": 5.66982078330226e-11,
        "beta_only_error_abs": 0.00047668623787930657,
        "bulk_abs": 62.8338934154707,
        "label": "s=1/2+0.3i",
        "n": 512,
        "raw_abs": 63.550257333267,
        "rung1_ratio_abs_error": 0.00021300625721487683,
        "rung1_ratio_im": 0.00010583577817273151,
        "rung1_ratio_re": 1.000184852518704
      },
      {
        "after_j1_abs": 2.5384104787829342e-08,
        "after_j2_abs": 7.085083676184641e-12,
        "beta_only_error_abs": 0.00023832109947817564,
        "bulk_abs": 88.86054424486417,
        "label": "s=1/2+0.3i",
        "n": 1024,
        "raw_abs": 90.04795233277494,
        "rung1_ratio_abs_error": 0.00010652204837557223,
        "rung1_ratio_im": 5.290736212766612e-05,
        "rung1_ratio_re": 1.0000924540849438
      },
      {
        "after_j1_abs": 6.346589282563555e-09,
        "after_j2_abs": 8.85498291736515e-13,
        "beta_only_error_abs": 0.00011915504251178085,
        "bulk_abs": 125.6677868309414,
        "label": "s=1/2+0.3i",
        "n": 2048,
        "raw_abs": 127.28212562129117,
        "rung1_ratio_abs_error": 5.3265750061137704e-05,
        "rung1_ratio_im": 2.6451047148777614e-05,
        "rung1_ratio_re": 1.000046233994358
      },
      {
        "after_j1_abs": 1.586717676014773e-09,
        "after_j2_abs": 1.106787088346888e-13,
        "beta_only_error_abs": 5.9576144154048284e-05,
        "bulk_abs": 177.72108848972834,
        "label": "s=1/2+0.3i",
        "n": 4096,
        "raw_abs": 179.69839060131108,
        "rung1_ratio_abs_error": 2.6634055989850735e-05,
        "rung1_ratio_im": 1.3224864823956154e-05,
        "rung1_ratio_re": 1.000023118734586
      },
      {
        "after_j1_abs": 3.96688211529123e-10,
        "after_j2_abs": 1.3834302357226843e-14,
        "beta_only_error_abs": 2.9787727764700874e-05,
        "bulk_abs": 251.3355736618828,
        "label": "s=1/2+0.3i",
        "n": 8192,
        "raw_abs": 253.5946397434469,
        "rung1_ratio_abs_error": 1.3317323171084465e-05,
        "rung1_ratio_im": 6.6122676904272024e-06,
        "rung1_ratio_re": 1.0000115598015742
      }
    ],
    "s=1/2+2i": [
      {
        "after_j1_abs": 3.941381842652944e-05,
        "after_j2_abs": 1.7375588596490562e-07,
        "beta_only_error_abs": 0.008706049544350253,
        "bulk_abs": 14.179581358103242,
        "label": "s=1/2+2i",
        "n": 128,
        "raw_abs": 15.034391742799148,
        "rung1_ratio_abs_error": 0.004531297844236925,
        "rung1_ratio_im": 0.004440894821436836,
        "rung1_ratio_re": 1.0009006183087867
      },
      {
        "after_j1_abs": 9.85117233540708e-06,
        "after_j2_abs": 2.1716562353764102e-08,
        "beta_only_error_abs": 0.004351054914424249,
        "bulk_abs": 20.052956265402315,
        "label": "s=1/2+2i",
        "n": 256,
        "raw_abs": 20.890209176243488,
        "rung1_ratio_abs_error": 0.0022651241492801064,
        "rung1_ratio_im": 0.0022189406462792306,
        "rung1_ratio_re": 1.0004550712251306
      },
      {
        "after_j1_abs": 2.4625020191722695e-06,
        "after_j2_abs": 2.7143785729037157e-09,
        "beta_only_error_abs": 0.0021750312449631895,
        "bulk_abs": 28.359162716206484,
        "label": "s=1/2+2i",
        "n": 512,
        "raw_abs": 27.844014290181217,
        "rung1_ratio_abs_error": 0.0011324282230309062,
        "rung1_ratio_im": 0.001109089179598742,
        "rung1_ratio_re": 1.0002287244455976
      },
      {
        "after_j1_abs": 6.155887607310235e-07,
        "after_j2_abs": 3.3928505763322905e-10,
        "beta_only_error_abs": 0.0010873911017490899,
        "bulk_abs": 40.10591253080463,
        "label": "s=1/2+2i",
        "n": 1024,
        "raw_abs": 39.08578230654275,
        "rung1_ratio_abs_error": 0.0005661803166088392,
        "rung1_ratio_im": 0.0005544487485275387,
        "rung1_ratio_re": 1.0001146592175603
      },
      {
        "after_j1_abs": 1.538925746243644e-07,
        "after_j2_abs": 4.240985691420245e-11,
        "beta_only_error_abs": 0.0005436643622837713,
        "bulk_abs": 56.71832543241297,
        "label": "s=1/2+2i",
        "n": 2048,
        "raw_abs": 56.88293382188445,
        "rung1_ratio_abs_error": 0.00028308166809641675,
        "rung1_ratio_im": 0.0002772003445966435,
        "rung1_ratio_re": 1.0000574038306018
      },
      {
        "after_j1_abs": 3.847256530220952e-08,
        "after_j2_abs": 5.3011833839676954e-12,
        "beta_only_error_abs": 0.00027182437669645576,
        "bulk_abs": 80.21182506160926,
        "label": "s=1/2+2i",
        "n": 4096,
        "raw_abs": 81.29024677084955,
        "rung1_ratio_abs_error": 0.00014153870631226077,
        "rung1_ratio_im": 0.00013859415621756676,
        "rung1_ratio_re": 1.0000287204673863
      },
      {
        "after_j1_abs": 9.618068943259989e-09,
        "after_j2_abs": 6.626448687684448e-13,
        "beta_only_error_abs": 0.00013591023632485532,
        "bulk_abs": 113.43665086482594,
        "label": "s=1/2+2i",
        "n": 8192,
        "raw_abs": 113.68302010754194,
        "rung1_ratio_abs_error": 7.076882057422719e-05,
        "rung1_ratio_im": 6.929557300589114e-05,
        "rung1_ratio_re": 1.0000143648712925
      }
    ],
    "s=1/4": [
      {
        "after_j1_abs": 1.8783001379109315e-07,
        "after_j2_abs": 1.0237769435898335e-09,
        "beta_only_error_abs": 0.0005222299176566996,
        "bulk_abs": 64.48075701506583,
        "label": "s=1/4",
        "n": 128,
        "raw_abs": 62.85367797462439,
        "rung1_ratio_abs_error": 0.000359798602904167,
        "rung1_ratio_im": 0.0,
        "rung1_ratio_re": 1.0003597986029042
      },
      {
        "after_j1_abs": 4.7085568954463e-08,
        "after_j2_abs": 1.2787872920774578e-10,
        "beta_only_error_abs": 0.0002610681293904087,
        "bulk_abs": 108.44327485362932,
        "label": "s=1/4",
        "n": 256,
        "raw_abs": 106.81645697497615,
        "rung1_ratio_abs_error": 0.00018038993433292246,
        "rung1_ratio_im": 0.0,
        "rung1_ratio_re": 1.000180389934333
      },
      {
        "after_j1_abs": 1.1787382969572778e-08,
        "after_j2_abs": 1.5978951344909304e-11,
        "beta_only_error_abs": 0.0001305223092936967,
        "bulk_abs": 182.37912216558036,
        "label": "s=1/4",
        "n": 512,
        "raw_abs": 180.7524348327473,
        "rung1_ratio_abs_error": 9.031749162443532e-05,
        "rung1_ratio_im": 0.0,
        "rung1_ratio_re": 1.0000903174916245
      },
      {
        "after_j1_abs": 2.948843481077167e-09,
        "after_j2_abs": 1.9969991522546718e-12,
        "beta_only_error_abs": 6.525820979884463e-05,
        "bulk_abs": 306.7239000923116,
        "label": "s=1/4",
        "n": 1024,
        "raw_abs": 305.09727802357804,
        "rung1_ratio_abs_error": 4.518936002867661e-05,
        "rung1_ratio_im": 0.0,
        "rung1_ratio_re": 1.0000451893600286
      },
      {
        "after_j1_abs": 7.374605183252886e-10,
        "after_j2_abs": 2.496017320668429e-13,
        "beta_only_error_abs": 3.2628367938200103e-05,
        "bulk_abs": 515.8460561205267,
        "label": "s=1/4",
        "n": 2048,
        "raw_abs": 514.2194666816349,
        "rung1_ratio_abs_error": 2.260233144511467e-05,
        "rung1_ratio_im": 0.0,
        "rung1_ratio_re": 1.0000226023314451
      },
      {
        "after_j1_abs": 1.8439633124706488e-10,
        "after_j2_abs": 3.119876727397641e-14,
        "beta_only_error_abs": 1.6313999635172135e-05,
        "bulk_abs": 867.5461988290346,
        "label": "s=1/4",
        "n": 4096,
        "raw_abs": 865.9196257045112,
        "rung1_ratio_abs_error": 1.1303078314142192e-05,
        "rung1_ratio_im": 0.0,
        "rung1_ratio_re": 1.0000113030783142
      },
      {
        "after_j1_abs": 4.610298274830296e-11,
        "after_j2_abs": 3.899755281750952e-15,
        "beta_only_error_abs": 8.156953722403192e-06,
        "bulk_abs": 1459.0329773246428,
        "label": "s=1/4",
        "n": 8192,
        "raw_abs": 1457.4064123571654,
        "rung1_ratio_abs_error": 5.652017271660436e-06,
        "rung1_ratio_im": 0.0,
        "rung1_ratio_re": 1.0000056520172718
      }
    ],
    "s=3/4": [
      {
        "after_j1_abs": 3.914691391176633e-06,
        "after_j2_abs": 3.331604443907921e-09,
        "beta_only_error_abs": 0.003759202944069817,
        "bulk_abs": 24.94535599608658,
        "label": "s=3/4",
        "n": 128,
        "raw_abs": 18.059026019252062,
        "rung1_ratio_abs_error": 0.001042447643901714,
        "rung1_ratio_im": 0.0,
        "rung1_ratio_re": 1.0010424476439017
      },
      {
        "after_j1_abs": 9.790910314066138e-07,
        "after_j2_abs": 4.1471749852141364e-10,
        "beta_only_error_abs": 0.0018786232173707267,
        "bulk_abs": 29.66519483682195,
        "label": "s=3/4",
        "n": 256,
        "raw_abs": 22.780745439714135,
        "rung1_ratio_abs_error": 0.0005214465391349013,
        "rung1_ratio_im": 0.0,
        "rung1_ratio_re": 1.000521446539135
      },
      {
        "after_j1_abs": 2.448247060229236e-07,
        "after_j2_abs": 5.1731203360235006e-11,
        "beta_only_error_abs": 0.0009390668878756829,
        "bulk_abs": 35.27806076789065,
        "label": "s=3/4",
        "n": 512,
        "raw_abs": 28.394550927112327,
        "rung1_ratio_abs_error": 0.0002607786029190069,
        "rung1_ratio_im": 0.0,
        "rung1_ratio_re": 1.000260778602919
      },
      {
        "after_j1_abs": 6.121264969157868e-08,
        "after_j2_abs": 6.4596149922789825e-12,
        "beta_only_error_abs": 0.00046947224423452157,
        "bulk_abs": 41.952920868673914,
        "label": "s=3/4",
        "n": 1024,
        "raw_abs": 35.06988062253924,
        "rung1_ratio_abs_error": 0.00013040309147595433,
        "rung1_ratio_im": 0.0,
        "rung1_ratio_re": 1.000130403091476
      },
      {
        "after_j1_abs": 1.5303970299018793e-08,
        "after_j2_abs": 8.070276239442772e-13,
        "beta_only_error_abs": 0.000234720819762714,
        "bulk_abs": 49.89071199217316,
        "label": "s=3/4",
        "n": 2048,
        "raw_abs": 43.00790649746295,
        "rung1_ratio_abs_error": 6.52049878220773e-05,
        "rung1_ratio_im": 0.0,
        "rung1_ratio_re": 1.000065204987822
      },
      {
        "after_j1_abs": 3.8260934797283325e-09,
        "after_j2_abs": 1.0085193235183569e-13,
        "beta_only_error_abs": 0.00011735658398968724,
        "bulk_abs": 59.3303896736439,
        "label": "s=3/4",
        "n": 4096,
        "raw_abs": 52.447701543169465,
        "rung1_ratio_abs_error": 3.2603353754262136e-05,
        "rung1_ratio_im": 0.0,
        "rung1_ratio_re": 1.0000326033537543
      },
      {
        "after_j1_abs": 9.565359780813235e-10,
        "after_j2_abs": 1.2604833847578865e-14,
        "beta_only_error_abs": 5.8677335484081834e-05,
        "bulk_abs": 70.5561215357813,
        "label": "s=3/4",
        "n": 8192,
        "raw_abs": 63.67349208455537,
        "rung1_ratio_abs_error": 1.6301891753193063e-05,
        "rung1_ratio_im": 0.0,
        "rung1_ratio_re": 1.0000163018917532
      }
    ]
  },
  "elapsed_ms": 1865.787332993932,
  "endpoint_coefficients": [
    {
      "bulk_beta_at_n_max": {
        "abs": 1459.0329773246428,
        "im": 0.0,
        "re": 1459.0329773246428
      },
      "first_rung_coefficient": {
        "abs": 0.06682138721829228,
        "im": 0.0,
        "re": -0.06682138721829228
      },
      "label": "s=1/4",
      "s": {
        "abs": 0.25,
        "im": 0.0,
        "re": 0.25
      },
      "second_rung_coefficient": {
        "abs": 0.003094180507397046,
        "im": 0.0,
        "re": -0.003094180507397046
      },
      "two_zeta_s": {
        "abs": 1.6265568105237833,
        "im": 0.0,
        "re": -1.6265568105237833
      }
    },
    {
      "bulk_beta_at_n_max": {
        "abs": 284.34450804213543,
        "im": 0.0,
        "re": 284.34450804213543
      },
      "first_rung_coefficient": {
        "abs": 0.20788622497735457,
        "im": 0.0,
        "re": -0.20788622497735457
      },
      "label": "s=1/2",
      "s": {
        "abs": 0.5,
        "im": 0.0,
        "re": 0.5
      },
      "second_rung_coefficient": {
        "abs": 0.019113901417374776,
        "im": 0.0,
        "re": -0.019113901417374776
      },
      "two_zeta_s": {
        "abs": 2.9207090176191737,
        "im": 0.0,
        "re": -2.9207090176191737
      }
    },
    {
      "bulk_beta_at_n_max": {
        "abs": 70.5561215357813,
        "im": 0.0,
        "re": 70.5561215357813
      },
      "first_rung_coefficient": {
        "abs": 0.4806768963428659,
        "im": 0.0,
        "re": -0.4806768963428659
      },
      "label": "s=3/4",
      "s": {
        "abs": 0.75,
        "im": 0.0,
        "re": 0.75
      },
      "second_rung_coefficient": {
        "abs": 0.06419288876024694,
        "im": 0.0,
        "re": -0.06419288876024694
      },
      "two_zeta_s": {
        "abs": 6.882570773890445,
        "im": 0.0,
        "re": -6.882570773890445
      }
    },
    {
      "bulk_beta_at_n_max": {
        "abs": 251.3355736618828,
        "im": -235.78611603990214,
        "re": -87.03147747088698
      },
      "first_rung_coefficient": {
        "abs": 0.244018245040602,
        "im": -0.21234868693196862,
        "re": -0.12022037710373419
      },
      "label": "s=1/2+0.3i",
      "s": {
        "abs": 0.5830951894845301,
        "im": 0.3,
        "re": 0.5
      },
      "second_rung_coefficient": {
        "abs": 0.0266218852094428,
        "im": -0.026621627630665633,
        "re": 0.00011710849213212092
      },
      "two_zeta_s": {
        "abs": 2.533030032316604,
        "im": -1.7182638070583636,
        "re": -1.8611315466594929
      }
    },
    {
      "bulk_beta_at_n_max": {
        "abs": 113.43665086482594,
        "im": -104.92342722145813,
        "re": -43.11552132969975
      },
      "first_rung_coefficient": {
        "abs": 1.1133606600175596,
        "im": 0.7678507151323917,
        "re": 0.8062116586513807
      },
      "label": "s=1/2+2i",
      "s": {
        "abs": 2.0615528128088303,
        "im": 2.0,
        "re": 0.5
      },
      "second_rung_coefficient": {
        "abs": 0.6454528192230993,
        "im": 0.5480392482779869,
        "re": -0.34097261501467513
      },
      "two_zeta_s": {
        "abs": 1.0792662512922897,
        "im": -0.6232926768714795,
        "re": 0.8810913006816589
      }
    }
  ],
  "formula": "S_n(s)=n^(1-s)B(1-s,1-s)+2*sum_j (s)_j*zeta(s-j)*n^(-j)/j!+R",
  "gauss_circle_rows": [
    {
      "area_channel": 804.247719318987,
      "radius": 16,
      "raw_count": 797,
      "relative_area_error": -0.00901179965437041,
      "residual": -7.247719318987038,
      "residual_over_sqrt_r": -1.8119298297467594
    },
    {
      "area_channel": 3216.990877275948,
      "radius": 32,
      "raw_count": 3209,
      "relative_area_error": -0.00248396019161689,
      "residual": -7.990877275948151,
      "residual_over_sqrt_r": -1.4126008773631058
    },
    {
      "area_channel": 12867.963509103793,
      "radius": 64,
      "raw_count": 12853,
      "relative_area_error": -0.001162849824154868,
      "residual": -14.963509103792603,
      "residual_over_sqrt_r": -1.8704386379740754
    },
    {
      "area_channel": 51471.85403641517,
      "radius": 128,
      "raw_count": 51433,
      "relative_area_error": -0.000754859857732773,
      "residual": -38.85403641517041,
      "residual_over_sqrt_r": -3.4342440782045065
    },
    {
      "area_channel": 205887.41614566068,
      "radius": 256,
      "raw_count": 205861,
      "relative_area_error": -0.00012830383787026996,
      "residual": -26.41614566068165,
      "residual_over_sqrt_r": -1.6510091037926031
    }
  ],
  "mpmath_dps": 80,
  "n_values": [
    128,
    256,
    512,
    1024,
    2048,
    4096,
    8192
  ],
  "slope_rows": [
    {
      "after_j1_order": 1.9997191900056992,
      "after_j2_order": 3.0000770245480473,
      "beta_only_order": 1.0000187417735213,
      "label": "s=1/4",
      "pass_endpoint_decay": true,
      "rung1_ratio_abs_error_at_max_n": 5.652017271660436e-06
    },
    {
      "after_j1_order": 1.9998871239324088,
      "after_j2_order": 3.000184638871129,
      "beta_only_order": 1.0000372293681477,
      "label": "s=1/2",
      "pass_endpoint_decay": true,
      "rung1_ratio_abs_error_at_max_n": 1.122325731235686e-05
    },
    {
      "after_j1_order": 1.9999562277156044,
      "after_j2_order": 3.000436113441816,
      "beta_only_order": 1.0000540835399565,
      "label": "s=3/4",
      "pass_endpoint_decay": true,
      "rung1_ratio_abs_error_at_max_n": 1.6301891753193063e-05
    },
    {
      "after_j1_order": 1.9999264168680986,
      "after_j2_order": 3.00012853709064,
      "beta_only_order": 1.0000383452591581,
      "label": "s=1/2+0.3i",
      "pass_endpoint_decay": true,
      "rung1_ratio_abs_error_at_max_n": 1.3317323171084465e-05
    },
    {
      "after_j1_order": 2.000024912874902,
      "after_j2_order": 3.000015211602059,
      "beta_only_order": 1.0000476130309393,
      "label": "s=1/2+2i",
      "pass_endpoint_decay": true,
      "rung1_ratio_abs_error_at_max_n": 7.076882057422719e-05
    }
  ]
}
